{
"meta":{"test_sets":[],"test_metrics":[],"learn_metrics":[{"best_value":"Min","name":"RMSE"}],"launch_mode":"Train","parameters":"","iteration_count":1000,"learn_sets":["learn"],"name":"experiment"},
"iterations":[
{"learn":[14.59871775],"iteration":0,"passed_time":0.6291213656,"remaining_time":628.4922442},
{"learn":[14.22518863],"iteration":1,"passed_time":0.6311519166,"remaining_time":314.9448064},
{"learn":[13.8866124],"iteration":2,"passed_time":0.6458556794,"remaining_time":214.6393708},
{"learn":[13.52356875],"iteration":3,"passed_time":0.6475637401,"remaining_time":161.2433713},
{"learn":[13.18870211],"iteration":4,"passed_time":0.6492145858,"remaining_time":129.1937026},
{"learn":[12.9124226],"iteration":5,"passed_time":0.6508224965,"remaining_time":107.8195936},
{"learn":[12.60003351],"iteration":6,"passed_time":0.6524516902,"remaining_time":92.55493262},
{"learn":[12.32990573],"iteration":7,"passed_time":0.6541764025,"remaining_time":81.1178739},
{"learn":[12.0660619],"iteration":8,"passed_time":0.6559962721,"remaining_time":72.23247841},
{"learn":[11.77309809],"iteration":9,"passed_time":0.6594082254,"remaining_time":65.28141431},
{"learn":[11.49227636],"iteration":10,"passed_time":0.6610404488,"remaining_time":59.43354581},
{"learn":[11.26264833],"iteration":11,"passed_time":0.6626410508,"remaining_time":54.55744651},
{"learn":[11.04260393],"iteration":12,"passed_time":0.6643660057,"remaining_time":50.44071136},
{"learn":[10.79916926],"iteration":13,"passed_time":0.6660305048,"remaining_time":46.90757698},
{"learn":[10.5541002],"iteration":14,"passed_time":0.6676851147,"remaining_time":43.84465586},
{"learn":[10.31918115],"iteration":15,"passed_time":0.6694225477,"remaining_time":41.16948668},
{"learn":[10.10004441],"iteration":16,"passed_time":0.6716672324,"remaining_time":38.83816997},
{"learn":[9.894556723],"iteration":17,"passed_time":0.6738785507,"remaining_time":36.76381871},
{"learn":[9.690174082],"iteration":18,"passed_time":0.675859925,"remaining_time":34.89571507},
{"learn":[9.506034866],"iteration":19,"passed_time":0.6777515296,"remaining_time":33.20982495},
{"learn":[9.338524633],"iteration":20,"passed_time":0.679442253,"remaining_time":31.67495075},
{"learn":[9.170203312],"iteration":21,"passed_time":0.6811339111,"remaining_time":30.27949841},
{"learn":[9.010299969],"iteration":22,"passed_time":0.6828849475,"remaining_time":29.00776494},
{"learn":[8.843866678],"iteration":23,"passed_time":0.6847066153,"remaining_time":27.84473569},
{"learn":[8.690548059],"iteration":24,"passed_time":0.6874965051,"remaining_time":26.8123637},
{"learn":[8.555307687],"iteration":25,"passed_time":0.6891976072,"remaining_time":25.81840267},
{"learn":[8.413851302],"iteration":26,"passed_time":0.6907947109,"remaining_time":24.89419458},
{"learn":[8.29256019],"iteration":27,"passed_time":0.6923454974,"remaining_time":24.03427941},
{"learn":[8.162193833],"iteration":28,"passed_time":0.6939073842,"remaining_time":23.23393345},
{"learn":[8.040736294],"iteration":29,"passed_time":0.695591291,"remaining_time":22.49078507},
{"learn":[7.921220278],"iteration":30,"passed_time":0.6972883858,"remaining_time":21.79588535},
{"learn":[7.809589039],"iteration":31,"passed_time":0.7003187238,"remaining_time":21.1846414},
{"learn":[7.699675801],"iteration":32,"passed_time":0.7020909138,"remaining_time":20.57339132},
{"learn":[7.60645267],"iteration":33,"passed_time":0.7037080977,"remaining_time":19.99358889},
{"learn":[7.498880302],"iteration":34,"passed_time":0.7053235936,"remaining_time":19.44677908},
{"learn":[7.401158744],"iteration":35,"passed_time":0.7068747388,"remaining_time":18.92853467},
{"learn":[7.306431077],"iteration":36,"passed_time":0.7085020271,"remaining_time":18.44020141},
{"learn":[7.223863468],"iteration":37,"passed_time":0.7103213508,"remaining_time":17.98234578},
{"learn":[7.143477682],"iteration":38,"passed_time":0.7119732663,"remaining_time":17.54375151},
{"learn":[7.062817131],"iteration":39,"passed_time":0.7155417226,"remaining_time":17.17300134},
{"learn":[6.990793435],"iteration":40,"passed_time":0.7171638184,"remaining_time":16.77463663},
{"learn":[6.931862224],"iteration":41,"passed_time":0.7188580802,"remaining_time":16.3968105},
{"learn":[6.858296558],"iteration":42,"passed_time":0.7204737661,"remaining_time":16.0347301},
{"learn":[6.786268161],"iteration":43,"passed_time":0.7221141951,"remaining_time":15.68957206},
{"learn":[6.717118549],"iteration":44,"passed_time":0.7238327084,"remaining_time":15.36133859},
{"learn":[6.652948106],"iteration":45,"passed_time":0.7254213639,"remaining_time":15.04460829},
{"learn":[6.589686076],"iteration":46,"passed_time":0.7285947715,"remaining_time":14.77342164},
{"learn":[6.531283097],"iteration":47,"passed_time":0.7302847248,"remaining_time":14.48398038},
{"learn":[6.471368031],"iteration":48,"passed_time":0.7319265,"remaining_time":14.20534901},
{"learn":[6.416481395],"iteration":49,"passed_time":0.7337105942,"remaining_time":13.94050129},
{"learn":[6.369870822],"iteration":50,"passed_time":0.7353227791,"remaining_time":13.68277093},
{"learn":[6.325678067],"iteration":51,"passed_time":0.7368887465,"remaining_time":13.43404869},
{"learn":[6.275766122],"iteration":52,"passed_time":0.7385250886,"remaining_time":13.19591055},
{"learn":[6.224773967],"iteration":53,"passed_time":0.7400820825,"remaining_time":12.96514167},
{"learn":[6.182249254],"iteration":54,"passed_time":0.7431218925,"remaining_time":12.76818524},
{"learn":[6.139904173],"iteration":55,"passed_time":0.7450090172,"remaining_time":12.55872343},
{"learn":[6.100525536],"iteration":56,"passed_time":0.746682167,"remaining_time":12.35300497},
{"learn":[6.062568564],"iteration":57,"passed_time":0.7483552298,"remaining_time":12.15432115},
{"learn":[6.030559288],"iteration":58,"passed_time":0.7504941732,"remaining_time":11.96974605},
{"learn":[5.997931376],"iteration":59,"passed_time":0.7528737315,"remaining_time":11.79502179},
{"learn":[5.964103835],"iteration":60,"passed_time":0.7545993189,"remaining_time":11.61588132},
{"learn":[5.933729724],"iteration":61,"passed_time":0.7576782444,"remaining_time":11.4629386},
{"learn":[5.901932711],"iteration":62,"passed_time":0.7595567343,"remaining_time":11.29689936},
{"learn":[5.873727795],"iteration":63,"passed_time":0.7614956741,"remaining_time":11.13687423},
{"learn":[5.846485734],"iteration":64,"passed_time":0.7636471263,"remaining_time":10.9847702},
{"learn":[5.820630862],"iteration":65,"passed_time":0.7654786744,"remaining_time":10.83268306},
{"learn":[5.793646238],"iteration":66,"passed_time":0.7672677612,"remaining_time":10.68448987},
{"learn":[5.765388646],"iteration":67,"passed_time":0.7737546833,"remaining_time":10.60499066},
{"learn":[5.747073912],"iteration":68,"passed_time":0.7757368525,"remaining_time":10.46682623},
{"learn":[5.722315217],"iteration":69,"passed_time":0.7774185982,"remaining_time":10.32856138},
{"learn":[5.699970599],"iteration":70,"passed_time":0.779094052,"remaining_time":10.19406161},
{"learn":[5.682732647],"iteration":71,"passed_time":0.7807064917,"remaining_time":10.06243923},
{"learn":[5.663525791],"iteration":72,"passed_time":0.7823049057,"remaining_time":9.934200652},
{"learn":[5.642381613],"iteration":73,"passed_time":0.7838870215,"remaining_time":9.809180836},
{"learn":[5.621404779],"iteration":74,"passed_time":0.7858795663,"remaining_time":9.692514651},
{"learn":[5.602460129],"iteration":75,"passed_time":0.7899153195,"remaining_time":9.603707306},
{"learn":[5.587337574],"iteration":76,"passed_time":0.7923961983,"remaining_time":9.49846352},
{"learn":[5.572393026],"iteration":77,"passed_time":0.7942790394,"remaining_time":9.388785568},
{"learn":[5.558425806],"iteration":78,"passed_time":0.7965509358,"remaining_time":9.286372303},
{"learn":[5.541518902],"iteration":79,"passed_time":0.7984315235,"remaining_time":9.18196252},
{"learn":[5.526157283],"iteration":80,"passed_time":0.8035662785,"remaining_time":9.117005061},
{"learn":[5.511746977],"iteration":81,"passed_time":0.8054190889,"remaining_time":9.016764922},
{"learn":[5.504975022],"iteration":82,"passed_time":0.8063195335,"remaining_time":8.908373642},
{"learn":[5.493980522],"iteration":83,"passed_time":0.8078771245,"remaining_time":8.809707691},
{"learn":[5.480745463],"iteration":84,"passed_time":0.809525316,"remaining_time":8.714301931},
{"learn":[5.464052013],"iteration":85,"passed_time":0.8110811811,"remaining_time":8.620095343},
{"learn":[5.449143727],"iteration":86,"passed_time":0.8127149036,"remaining_time":8.528835713},
{"learn":[5.438255432],"iteration":87,"passed_time":0.8147027865,"remaining_time":8.443283424},
{"learn":[5.425927931],"iteration":88,"passed_time":0.8168452087,"remaining_time":8.361190844},
{"learn":[5.412331217],"iteration":89,"passed_time":0.8184635805,"remaining_time":8.275576203},
{"learn":[5.400691499],"iteration":90,"passed_time":0.8200962534,"remaining_time":8.191950487},
{"learn":[5.391618744],"iteration":91,"passed_time":0.8216830817,"remaining_time":8.109654763},
{"learn":[5.380766572],"iteration":92,"passed_time":0.8233459097,"remaining_time":8.029835915},
{"learn":[5.372207183],"iteration":93,"passed_time":0.8249742572,"remaining_time":7.951347628},
{"learn":[5.362918837],"iteration":94,"passed_time":0.8265653054,"remaining_time":7.87412212},
{"learn":[5.348292324],"iteration":95,"passed_time":0.8305038257,"remaining_time":7.820577692},
{"learn":[5.339772295],"iteration":96,"passed_time":0.8322105571,"remaining_time":7.747279723},
{"learn":[5.331515983],"iteration":97,"passed_time":0.8337519608,"remaining_time":7.673921108},
{"learn":[5.323861644],"iteration":98,"passed_time":0.8353877753,"remaining_time":7.602872582},
{"learn":[5.313277281],"iteration":99,"passed_time":0.8369947282,"remaining_time":7.532952553},
{"learn":[5.30685627],"iteration":100,"passed_time":0.8385585013,"remaining_time":7.464000917},
{"learn":[5.29652059],"iteration":101,"passed_time":0.8402150269,"remaining_time":7.397187198},
{"learn":[5.288350766],"iteration":102,"passed_time":0.841917778,"remaining_time":7.332041232},
{"learn":[5.27993346],"iteration":103,"passed_time":0.8461774709,"remaining_time":7.290144364},
{"learn":[5.271789139],"iteration":104,"passed_time":0.8479258123,"remaining_time":7.227558114},
{"learn":[5.262684686],"iteration":105,"passed_time":0.8494494988,"remaining_time":7.164225018},
{"learn":[5.251619772],"iteration":106,"passed_time":0.8511331181,"remaining_time":7.103382004},
{"learn":[5.241012171],"iteration":107,"passed_time":0.8527366655,"remaining_time":7.0429732},
{"learn":[5.232684032],"iteration":108,"passed_time":0.8542746911,"remaining_time":6.983107796},
{"learn":[5.224267141],"iteration":109,"passed_time":0.8560042325,"remaining_time":6.925852427},
{"learn":[5.216324968],"iteration":110,"passed_time":0.8579248988,"remaining_time":6.871128244},
{"learn":[5.211102527],"iteration":111,"passed_time":0.8603749125,"remaining_time":6.821543949},
{"learn":[5.206364257],"iteration":112,"passed_time":0.8621691591,"remaining_time":6.767646408},
{"learn":[5.196937641],"iteration":113,"passed_time":0.8640098759,"remaining_time":6.715024124},
{"learn":[5.190746047],"iteration":114,"passed_time":0.865849119,"remaining_time":6.663273655},
{"learn":[5.181885213],"iteration":115,"passed_time":0.8675230748,"remaining_time":6.611124122},
{"learn":[5.178293568],"iteration":116,"passed_time":0.8687619333,"remaining_time":6.556553736},
{"learn":[5.170991438],"iteration":117,"passed_time":0.8705130751,"remaining_time":6.506716375},
{"learn":[5.166257212],"iteration":118,"passed_time":0.8741493884,"remaining_time":6.471643791},
{"learn":[5.161421246],"iteration":119,"passed_time":0.8757578372,"remaining_time":6.422224139},
{"learn":[5.158223542],"iteration":120,"passed_time":0.8774184856,"remaining_time":6.373973958},
{"learn":[5.15470988],"iteration":121,"passed_time":0.8786760276,"remaining_time":6.323586494},
{"learn":[5.146388143],"iteration":122,"passed_time":0.880291359,"remaining_time":6.276548958},
{"learn":[5.139529364],"iteration":123,"passed_time":0.8818889163,"remaining_time":6.230118473},
{"learn":[5.134276023],"iteration":124,"passed_time":0.883442682,"remaining_time":6.184098774},
{"learn":[5.128536065],"iteration":125,"passed_time":0.8851386085,"remaining_time":6.139770983},
{"learn":[5.123300353],"iteration":126,"passed_time":0.8879853889,"remaining_time":6.104025547},
{"learn":[5.116200518],"iteration":127,"passed_time":0.889683592,"remaining_time":6.06096947},
{"learn":[5.108728704],"iteration":128,"passed_time":0.8914876714,"remaining_time":6.019269471},
{"learn":[5.104075866],"iteration":129,"passed_time":0.8930379452,"remaining_time":5.97648471},
{"learn":[5.100317606],"iteration":130,"passed_time":0.8945990935,"remaining_time":5.93440162},
{"learn":[5.095814182],"iteration":131,"passed_time":0.8963161046,"remaining_time":5.893957415},
{"learn":[5.092146915],"iteration":132,"passed_time":0.8979997133,"remaining_time":5.85387783},
{"learn":[5.085258329],"iteration":133,"passed_time":0.8997006082,"remaining_time":5.814483035},
{"learn":[5.079219421],"iteration":134,"passed_time":0.9031584002,"remaining_time":5.786903824},
{"learn":[5.076476829],"iteration":135,"passed_time":0.9047658594,"remaining_time":5.747924284},
{"learn":[5.072133867],"iteration":136,"passed_time":0.906325495,"remaining_time":5.709189067},
{"learn":[5.067031564],"iteration":137,"passed_time":0.9078551885,"remaining_time":5.670805598},
{"learn":[5.061358312],"iteration":138,"passed_time":0.9094944169,"remaining_time":5.633630885},
{"learn":[5.056759124],"iteration":139,"passed_time":0.9111337255,"remaining_time":5.596964314},
{"learn":[5.050254],"iteration":140,"passed_time":0.9128273121,"remaining_time":5.561125256},
{"learn":[5.048376474],"iteration":141,"passed_time":0.9139802047,"remaining_time":5.52250011},
{"learn":[5.042603751],"iteration":142,"passed_time":0.9158880432,"remaining_time":5.488923447},
{"learn":[5.037477349],"iteration":143,"passed_time":0.918533371,"remaining_time":5.460170594},
{"learn":[5.03230489],"iteration":144,"passed_time":0.9202113842,"remaining_time":5.426074024},
{"learn":[5.025976187],"iteration":145,"passed_time":0.9218741215,"remaining_time":5.39233219},
{"learn":[5.01952451],"iteration":146,"passed_time":0.9234493389,"remaining_time":5.358518953},
{"learn":[5.017569424],"iteration":147,"passed_time":0.9251839088,"remaining_time":5.326058718},
{"learn":[5.008962367],"iteration":148,"passed_time":0.9267983729,"remaining_time":5.293324935},
{"learn":[5.003880266],"iteration":149,"passed_time":0.9286385021,"remaining_time":5.262284845},
{"learn":[4.996387564],"iteration":150,"passed_time":0.9305478708,"remaining_time":5.23202081},
{"learn":[4.993361683],"iteration":151,"passed_time":0.9333795425,"remaining_time":5.207275342},
{"learn":[4.99005752],"iteration":152,"passed_time":0.9349879955,"remaining_time":5.176044655},
{"learn":[4.986908764],"iteration":153,"passed_time":0.9365292746,"remaining_time":5.144829651},
{"learn":[4.985207175],"iteration":154,"passed_time":0.9381818336,"remaining_time":5.11460419},
{"learn":[4.979003494],"iteration":155,"passed_time":0.9398009776,"remaining_time":5.084564264},
{"learn":[4.973142217],"iteration":156,"passed_time":0.9413649617,"remaining_time":5.054590208},
{"learn":[4.967056696],"iteration":157,"passed_time":0.9475596816,"remaining_time":5.049653493},
{"learn":[4.961460696],"iteration":158,"passed_time":0.9496318373,"remaining_time":5.022895441},
{"learn":[4.954240363],"iteration":159,"passed_time":0.9518691066,"remaining_time":4.99731281},
{"learn":[4.952320707],"iteration":160,"passed_time":0.9536942184,"remaining_time":4.969872355},
{"learn":[4.948337777],"iteration":161,"passed_time":0.9556415036,"remaining_time":4.943380123},
{"learn":[4.943228639],"iteration":162,"passed_time":0.9574741615,"remaining_time":4.916600449},
{"learn":[4.938545759],"iteration":163,"passed_time":0.9592774861,"remaining_time":4.889975478},
{"learn":[4.935330572],"iteration":164,"passed_time":0.9634438895,"remaining_time":4.875609986},
{"learn":[4.932051543],"iteration":165,"passed_time":0.9652434442,"remaining_time":4.849476099},
{"learn":[4.928964153],"iteration":166,"passed_time":0.9670610346,"remaining_time":4.823723604},
{"learn":[4.922860227],"iteration":167,"passed_time":0.968787189,"remaining_time":4.797803222},
{"learn":[4.917668772],"iteration":168,"passed_time":0.9705621598,"remaining_time":4.7724092},
{"learn":[4.910365386],"iteration":169,"passed_time":0.972302964,"remaining_time":4.747126236},
{"learn":[4.906457206],"iteration":170,"passed_time":0.9739944223,"remaining_time":4.721879392},
{"learn":[4.901996508],"iteration":171,"passed_time":0.9780730504,"remaining_time":4.708398173},
{"learn":[4.896816173],"iteration":172,"passed_time":0.9798552741,"remaining_time":4.684048044},
{"learn":[4.891123132],"iteration":173,"passed_time":0.9816629879,"remaining_time":4.660078322},
{"learn":[4.887630202],"iteration":174,"passed_time":0.9834569217,"remaining_time":4.636296917},
{"learn":[4.885259712],"iteration":175,"passed_time":0.9852916142,"remaining_time":4.612956194},
{"learn":[4.880659728],"iteration":176,"passed_time":0.9870256228,"remaining_time":4.589390325},
{"learn":[4.877299723],"iteration":177,"passed_time":0.9888569773,"remaining_time":4.5665193},
{"learn":[4.874038772],"iteration":178,"passed_time":0.9932213513,"remaining_time":4.555501282},
{"learn":[4.86943698],"iteration":179,"passed_time":0.9951069584,"remaining_time":4.533265033},
{"learn":[4.861268711],"iteration":180,"passed_time":0.9969844783,"remaining_time":4.511217059},
{"learn":[4.858673056],"iteration":181,"passed_time":0.998693077,"remaining_time":4.488631522},
{"learn":[4.854036207],"iteration":182,"passed_time":1.001671117,"remaining_time":4.471941545},
{"learn":[4.85130244],"iteration":183,"passed_time":1.003974214,"remaining_time":4.452407385},
{"learn":[4.847510084],"iteration":184,"passed_time":1.009373463,"remaining_time":4.446699312},
{"learn":[4.845691673],"iteration":185,"passed_time":1.011822274,"remaining_time":4.428082427},
{"learn":[4.842058646],"iteration":186,"passed_time":1.014182889,"remaining_time":4.409255021},
{"learn":[4.838623675],"iteration":187,"passed_time":1.016965886,"remaining_time":4.392427124},
{"learn":[4.834602161],"iteration":188,"passed_time":1.020226045,"remaining_time":4.377795359},
{"learn":[4.830858976],"iteration":189,"passed_time":1.02639166,"remaining_time":4.375669708},
{"learn":[4.827590511],"iteration":190,"passed_time":1.029415497,"remaining_time":4.360194433},
{"learn":[4.822246226],"iteration":191,"passed_time":1.031898147,"remaining_time":4.342571367},
{"learn":[4.816686395],"iteration":192,"passed_time":1.037163065,"remaining_time":4.336738828},
{"learn":[4.814797121],"iteration":193,"passed_time":1.039614324,"remaining_time":4.319222398},
{"learn":[4.811639392],"iteration":194,"passed_time":1.041950155,"remaining_time":4.301383971},
{"learn":[4.804813432],"iteration":195,"passed_time":1.044379771,"remaining_time":4.28408845},
{"learn":[4.80251613],"iteration":196,"passed_time":1.046676568,"remaining_time":4.266402459},
{"learn":[4.800087884],"iteration":197,"passed_time":1.051514673,"remaining_time":4.259165493},
{"learn":[4.794773135],"iteration":198,"passed_time":1.054221944,"remaining_time":4.243375765},
{"learn":[4.791664833],"iteration":199,"passed_time":1.056862917,"remaining_time":4.227451668},
{"learn":[4.785989873],"iteration":200,"passed_time":1.059391585,"remaining_time":4.211213314},
{"learn":[4.782387142],"iteration":201,"passed_time":1.061795815,"remaining_time":4.194619111},
{"learn":[4.778623704],"iteration":202,"passed_time":1.067334878,"remaining_time":4.190472401},
{"learn":[4.775772178],"iteration":203,"passed_time":1.069910343,"remaining_time":4.174748201},
{"learn":[4.77023101],"iteration":204,"passed_time":1.090616749,"remaining_time":4.229464954},
{"learn":[4.764496689],"iteration":205,"passed_time":1.093174447,"remaining_time":4.213497627},
{"learn":[4.763138716],"iteration":206,"passed_time":1.095826989,"remaining_time":4.198023198},
{"learn":[4.758053283],"iteration":207,"passed_time":1.101058332,"remaining_time":4.192491343},
{"learn":[4.755063788],"iteration":208,"passed_time":1.103743728,"remaining_time":4.177326741},
{"learn":[4.752465267],"iteration":209,"passed_time":1.106698302,"remaining_time":4.163293612},
{"learn":[4.748067377],"iteration":210,"passed_time":1.109559328,"remaining_time":4.149015686},
{"learn":[4.744163298],"iteration":211,"passed_time":1.119851224,"remaining_time":4.162465872},
{"learn":[4.736670896],"iteration":212,"passed_time":1.123369735,"remaining_time":4.150666578},
{"learn":[4.73349255],"iteration":213,"passed_time":1.128365698,"remaining_time":4.14437121},
{"learn":[4.731864595],"iteration":214,"passed_time":1.130409877,"remaining_time":4.12731048},
{"learn":[4.728398311],"iteration":215,"passed_time":1.133167564,"remaining_time":4.112978567},
{"learn":[4.723865975],"iteration":216,"passed_time":1.135878544,"remaining_time":4.098584791},
{"learn":[4.723483365],"iteration":217,"passed_time":1.143122573,"remaining_time":4.100558956},
{"learn":[4.72095416],"iteration":218,"passed_time":1.150661223,"remaining_time":4.103499613},
{"learn":[4.716173382],"iteration":219,"passed_time":1.155081235,"remaining_time":4.095288016},
{"learn":[4.710563974],"iteration":220,"passed_time":1.164175887,"remaining_time":4.103588309},
{"learn":[4.707160263],"iteration":221,"passed_time":1.168346991,"remaining_time":4.094477291},
{"learn":[4.70408351],"iteration":222,"passed_time":1.175203692,"remaining_time":4.09476802},
{"learn":[4.702501831],"iteration":223,"passed_time":1.178752131,"remaining_time":4.083534169},
{"learn":[4.700269738],"iteration":224,"passed_time":1.182507521,"remaining_time":4.07308146},
{"learn":[4.695346302],"iteration":225,"passed_time":1.189323277,"remaining_time":4.073169099},
{"learn":[4.689769299],"iteration":226,"passed_time":1.191723967,"remaining_time":4.058161349},
{"learn":[4.687919514],"iteration":227,"passed_time":1.193698272,"remaining_time":4.041820466},
{"learn":[4.682982074],"iteration":228,"passed_time":1.196384326,"remaining_time":4.028001377},
{"learn":[4.679578702],"iteration":229,"passed_time":1.198682655,"remaining_time":4.012981061},
{"learn":[4.675751423],"iteration":230,"passed_time":1.204127348,"remaining_time":4.008545154},
{"learn":[4.672710726],"iteration":231,"passed_time":1.206276899,"remaining_time":3.993192493},
{"learn":[4.6690533],"iteration":232,"passed_time":1.208694687,"remaining_time":3.978836157},
{"learn":[4.667595702],"iteration":233,"passed_time":1.210712628,"remaining_time":3.963272961},
{"learn":[4.664241291],"iteration":234,"passed_time":1.212743888,"remaining_time":3.947868402},
{"learn":[4.662246999],"iteration":235,"passed_time":1.214757121,"remaining_time":3.932518816},
{"learn":[4.658668443],"iteration":236,"passed_time":1.217263734,"remaining_time":3.918870164},
{"learn":[4.658017572],"iteration":237,"passed_time":1.219878523,"remaining_time":3.905661488},
{"learn":[4.657656705],"iteration":238,"passed_time":1.222523223,"remaining_time":3.892636707},
{"learn":[4.653242871],"iteration":239,"passed_time":1.226158787,"remaining_time":3.88283616},
{"learn":[4.6507302],"iteration":240,"passed_time":1.22895774,"remaining_time":3.870451969},
{"learn":[4.647671336],"iteration":241,"passed_time":1.231613241,"remaining_time":3.857697673},
{"learn":[4.645506007],"iteration":242,"passed_time":1.233976404,"remaining_time":3.844115793},
{"learn":[4.641297906],"iteration":243,"passed_time":1.236337587,"remaining_time":3.830619738},
{"learn":[4.63798107],"iteration":244,"passed_time":1.24476474,"remaining_time":3.835907667},
{"learn":[4.635062318],"iteration":245,"passed_time":1.248067963,"remaining_time":3.825379042},
{"learn":[4.631606017],"iteration":246,"passed_time":1.250359806,"remaining_time":3.811825644},
{"learn":[4.630215494],"iteration":247,"passed_time":1.25559048,"remaining_time":3.807274358},
{"learn":[4.62729814],"iteration":248,"passed_time":1.25820691,"remaining_time":3.794832889},
{"learn":[4.624691756],"iteration":249,"passed_time":1.260853371,"remaining_time":3.782560112},
{"learn":[4.621840053],"iteration":250,"passed_time":1.26328384,"remaining_time":3.769719507},
{"learn":[4.619602091],"iteration":251,"passed_time":1.265667066,"remaining_time":3.756821291},
{"learn":[4.613584029],"iteration":252,"passed_time":1.271608371,"remaining_time":3.754511671},
{"learn":[4.6119388],"iteration":253,"passed_time":1.27391303,"remaining_time":3.7414926},
{"learn":[4.60870702],"iteration":254,"passed_time":1.276715064,"remaining_time":3.730010676},
{"learn":[4.604771557],"iteration":255,"passed_time":1.279978242,"remaining_time":3.719936767},
{"learn":[4.604231277],"iteration":256,"passed_time":1.282068213,"remaining_time":3.706524056},
{"learn":[4.600750354],"iteration":257,"passed_time":1.286660986,"remaining_time":3.700397098},
{"learn":[4.596488253],"iteration":258,"passed_time":1.289665258,"remaining_time":3.689737283},
{"learn":[4.59470784],"iteration":259,"passed_time":1.291947051,"remaining_time":3.677080069},
{"learn":[4.588818005],"iteration":260,"passed_time":1.294130364,"remaining_time":3.664223522},
{"learn":[4.585054174],"iteration":261,"passed_time":1.296586814,"remaining_time":3.652217819},
{"learn":[4.581471435],"iteration":262,"passed_time":1.302113594,"remaining_time":3.648888664},
{"learn":[4.577555199],"iteration":263,"passed_time":1.304705825,"remaining_time":3.637361695},
{"learn":[4.57457145],"iteration":264,"passed_time":1.307030809,"remaining_time":3.625160922},
{"learn":[4.573029224],"iteration":265,"passed_time":1.310900691,"remaining_time":3.617297397},
{"learn":[4.571326203],"iteration":266,"passed_time":1.317234653,"remaining_time":3.616228467},
{"learn":[4.571019224],"iteration":267,"passed_time":1.319876499,"remaining_time":3.605035812},
{"learn":[4.565766631],"iteration":268,"passed_time":1.323456058,"remaining_time":3.596454939},
{"learn":[4.563383471],"iteration":269,"passed_time":1.334979632,"remaining_time":3.609389376},
{"learn":[4.558165805],"iteration":270,"passed_time":1.338046224,"remaining_time":3.599393718},
{"learn":[4.55629209],"iteration":271,"passed_time":1.340518284,"remaining_time":3.587857761},
{"learn":[4.549383848],"iteration":272,"passed_time":1.34298441,"remaining_time":3.576372403},
{"learn":[4.546227503],"iteration":273,"passed_time":1.349214511,"remaining_time":3.574926039},
{"learn":[4.540620977],"iteration":274,"passed_time":1.351140911,"remaining_time":3.562098765},
{"learn":[4.532898237],"iteration":275,"passed_time":1.353291272,"remaining_time":3.549937975},
{"learn":[4.529757367],"iteration":276,"passed_time":1.355828268,"remaining_time":3.538858619},
{"learn":[4.52579294],"iteration":277,"passed_time":1.358446772,"remaining_time":3.528052409},
{"learn":[4.521572155],"iteration":278,"passed_time":1.360841128,"remaining_time":3.51672564},
{"learn":[4.518818099],"iteration":279,"passed_time":1.363305684,"remaining_time":3.505643186},
{"learn":[4.514012334],"iteration":280,"passed_time":1.365605369,"remaining_time":3.494200214},
{"learn":[4.508331416],"iteration":281,"passed_time":1.368159729,"remaining_time":3.483470516},
{"learn":[4.506038537],"iteration":282,"passed_time":1.370701836,"remaining_time":3.472767549},
{"learn":[4.505805643],"iteration":283,"passed_time":1.375641756,"remaining_time":3.468167244},
{"learn":[4.501550352],"iteration":284,"passed_time":1.377633501,"remaining_time":3.456168257},
{"learn":[4.494692643],"iteration":285,"passed_time":1.379853866,"remaining_time":3.44481},
{"learn":[4.489330245],"iteration":286,"passed_time":1.381889431,"remaining_time":3.433056321},
{"learn":[4.484826955],"iteration":287,"passed_time":1.383923593,"remaining_time":3.42136666},
{"learn":[4.478285428],"iteration":288,"passed_time":1.391177552,"remaining_time":3.422585603},
{"learn":[4.475311671],"iteration":289,"passed_time":1.393288597,"remaining_time":3.41115484},
{"learn":[4.471581298],"iteration":290,"passed_time":1.395462083,"remaining_time":3.399940264},
{"learn":[4.469164956],"iteration":291,"passed_time":1.397637149,"remaining_time":3.388791444},
{"learn":[4.462068024],"iteration":292,"passed_time":1.399843306,"remaining_time":3.377778898},
{"learn":[4.458540976],"iteration":293,"passed_time":1.404578843,"remaining_time":3.372900214},
{"learn":[4.455757458],"iteration":294,"passed_time":1.408230624,"remaining_time":3.365432508},
{"learn":[4.453027414],"iteration":295,"passed_time":1.410698979,"remaining_time":3.355175951},
{"learn":[4.450659338],"iteration":296,"passed_time":1.413094879,"remaining_time":3.344800338},
{"learn":[4.444696901],"iteration":297,"passed_time":1.415448423,"remaining_time":3.3343785},
{"learn":[4.442052813],"iteration":298,"passed_time":1.423392368,"remaining_time":3.337117225},
{"learn":[4.440036756],"iteration":299,"passed_time":1.426374874,"remaining_time":3.32820804},
{"learn":[4.435017051],"iteration":300,"passed_time":1.428834473,"remaining_time":3.31812391},
{"learn":[4.429962125],"iteration":301,"passed_time":1.431119054,"remaining_time":3.307685759},
{"learn":[4.427666256],"iteration":302,"passed_time":1.435887309,"remaining_time":3.303014702},
{"learn":[4.425030004],"iteration":303,"passed_time":1.438223737,"remaining_time":3.292775398},
{"learn":[4.422588771],"iteration":304,"passed_time":1.440349999,"remaining_time":3.282109015},
{"learn":[4.418936667],"iteration":305,"passed_time":1.44251609,"remaining_time":3.271588779},
{"learn":[4.416887976],"iteration":306,"passed_time":1.445174668,"remaining_time":3.262234673},
{"learn":[4.413773354],"iteration":307,"passed_time":1.450232731,"remaining_time":3.258315098},
{"learn":[4.411129391],"iteration":308,"passed_time":1.452319162,"remaining_time":3.247742852},
{"learn":[4.40850819],"iteration":309,"passed_time":1.454933012,"remaining_time":3.238399285},
{"learn":[4.404880292],"iteration":310,"passed_time":1.457744733,"remaining_time":3.229537368},
{"learn":[4.404593827],"iteration":311,"passed_time":1.460200089,"remaining_time":3.219928402},
{"learn":[4.402139942],"iteration":312,"passed_time":1.4621727,"remaining_time":3.209305574},
{"learn":[4.400284725],"iteration":313,"passed_time":1.464415819,"remaining_time":3.199328827},
{"learn":[4.395805521],"iteration":314,"passed_time":1.466249166,"remaining_time":3.188510091},
{"learn":[4.392838833],"iteration":315,"passed_time":1.468110756,"remaining_time":3.177809358},
{"learn":[4.389213061],"iteration":316,"passed_time":1.469873213,"remaining_time":3.166950802},
{"learn":[4.3861981],"iteration":317,"passed_time":1.471736021,"remaining_time":3.156364674},
{"learn":[4.385054234],"iteration":318,"passed_time":1.473474962,"remaining_time":3.145568805},
{"learn":[4.379364607],"iteration":319,"passed_time":1.475596528,"remaining_time":3.135642621},
{"learn":[4.378387619],"iteration":320,"passed_time":1.478021765,"remaining_time":3.12640741},
{"learn":[4.375816727],"iteration":321,"passed_time":1.47959041,"remaining_time":3.115410864},
{"learn":[4.374600202],"iteration":322,"passed_time":1.481247826,"remaining_time":3.104658757},
{"learn":[4.37098897],"iteration":323,"passed_time":1.483019137,"remaining_time":3.094200421},
{"learn":[4.367418484],"iteration":324,"passed_time":1.484645885,"remaining_time":3.083495299},
{"learn":[4.363584638],"iteration":325,"passed_time":1.486365175,"remaining_time":3.073037201},
{"learn":[4.360770706],"iteration":326,"passed_time":1.487922027,"remaining_time":3.062298239},
{"learn":[4.358675808],"iteration":327,"passed_time":1.49148858,"remaining_time":3.055732701},
{"learn":[4.354228195],"iteration":328,"passed_time":1.49355327,"remaining_time":3.046122323},
{"learn":[4.353773425],"iteration":329,"passed_time":1.495549239,"remaining_time":3.036418152},
{"learn":[4.351648009],"iteration":330,"passed_time":1.497598212,"remaining_time":3.026867686},
{"learn":[4.348209927],"iteration":331,"passed_time":1.499565786,"remaining_time":3.01719863},
{"learn":[4.345852733],"iteration":332,"passed_time":1.501360079,"remaining_time":3.007228747},
{"learn":[4.34237339],"iteration":333,"passed_time":1.50379955,"remaining_time":2.998594313},
{"learn":[4.340814362],"iteration":334,"passed_time":1.506008734,"remaining_time":2.989539726},
{"learn":[4.339707068],"iteration":335,"passed_time":1.508390766,"remaining_time":2.980867466},
{"learn":[4.335430786],"iteration":336,"passed_time":1.510540298,"remaining_time":2.971775126},
{"learn":[4.33521887],"iteration":337,"passed_time":1.513575196,"remaining_time":2.964457928},
{"learn":[4.328507238],"iteration":338,"passed_time":1.516070058,"remaining_time":2.956113005},
{"learn":[4.326140732],"iteration":339,"passed_time":1.521096241,"remaining_time":2.952716232},
{"learn":[4.323785636],"iteration":340,"passed_time":1.523512883,"remaining_time":2.944266833},
{"learn":[4.320632534],"iteration":341,"passed_time":1.525803749,"remaining_time":2.935610722},
{"learn":[4.31973724],"iteration":342,"passed_time":1.528010897,"remaining_time":2.926831368},
{"learn":[4.318000924],"iteration":343,"passed_time":1.530238728,"remaining_time":2.918129668},
{"learn":[4.312713628],"iteration":344,"passed_time":1.535405247,"remaining_time":2.915044744},
{"learn":[4.308220789],"iteration":345,"passed_time":1.5376969,"remaining_time":2.906513793},
{"learn":[4.305890947],"iteration":346,"passed_time":1.540321886,"remaining_time":2.898646085},
{"learn":[4.305137856],"iteration":347,"passed_time":1.542266003,"remaining_time":2.889532857},
{"learn":[4.304787172],"iteration":348,"passed_time":1.544167935,"remaining_time":2.880382021},
{"learn":[4.30350134],"iteration":349,"passed_time":1.546127613,"remaining_time":2.871379853},
{"learn":[4.30293809],"iteration":350,"passed_time":1.55052481,"remaining_time":2.86692479},
{"learn":[4.299548459],"iteration":351,"passed_time":1.552606142,"remaining_time":2.858206762},
{"learn":[4.294768408],"iteration":352,"passed_time":1.554539504,"remaining_time":2.849255124},
{"learn":[4.294581479],"iteration":353,"passed_time":1.556257581,"remaining_time":2.839950275},
{"learn":[4.292551604],"iteration":354,"passed_time":1.55800134,"remaining_time":2.830734829},
{"learn":[4.288628894],"iteration":355,"passed_time":1.559793787,"remaining_time":2.821649435},
{"learn":[4.287802767],"iteration":356,"passed_time":1.56151408,"remaining_time":2.81247494},
{"learn":[4.284566905],"iteration":357,"passed_time":1.56599581,"remaining_time":2.808294162},
{"learn":[4.27890232],"iteration":358,"passed_time":1.567626877,"remaining_time":2.799021806},
{"learn":[4.276938023],"iteration":359,"passed_time":1.56946277,"remaining_time":2.790156036},
{"learn":[4.273425094],"iteration":360,"passed_time":1.571215578,"remaining_time":2.781182146},
{"learn":[4.269726505],"iteration":361,"passed_time":1.572756782,"remaining_time":2.771875212},
{"learn":[4.265565857],"iteration":362,"passed_time":1.574436871,"remaining_time":2.762854785},
{"learn":[4.262117173],"iteration":363,"passed_time":1.576074646,"remaining_time":2.753800755},
{"learn":[4.259185148],"iteration":364,"passed_time":1.579443082,"remaining_time":2.747798238},
{"learn":[4.257668507],"iteration":365,"passed_time":1.581369197,"remaining_time":2.73931167},
{"learn":[4.253432436],"iteration":366,"passed_time":1.583160368,"remaining_time":2.730628101},
{"learn":[4.250216667],"iteration":367,"passed_time":1.584822812,"remaining_time":2.721760917},
{"learn":[4.24514828],"iteration":368,"passed_time":1.586419538,"remaining_time":2.712820403},
{"learn":[4.244015772],"iteration":369,"passed_time":1.588031466,"remaining_time":2.70394547},
{"learn":[4.240329192],"iteration":370,"passed_time":1.589809108,"remaining_time":2.695390645},
{"learn":[4.236718014],"iteration":371,"passed_time":1.591748182,"remaining_time":2.68714478},
{"learn":[4.233495944],"iteration":372,"passed_time":1.59800105,"remaining_time":2.686184071},
{"learn":[4.230357491],"iteration":373,"passed_time":1.600628597,"remaining_time":2.679127009},
{"learn":[4.227381215],"iteration":374,"passed_time":1.606845513,"remaining_time":2.678075855},
{"learn":[4.226169067],"iteration":375,"passed_time":1.617018146,"remaining_time":2.683562029},
{"learn":[4.225963861],"iteration":376,"passed_time":1.623757153,"remaining_time":2.683290998},
{"learn":[4.224346548],"iteration":377,"passed_time":1.62782477,"remaining_time":2.678589966},
{"learn":[4.222595381],"iteration":378,"passed_time":1.632026116,"remaining_time":2.674111393},
{"learn":[4.219700938],"iteration":379,"passed_time":1.637518988,"remaining_time":2.671741507},
{"learn":[4.216356207],"iteration":380,"passed_time":1.64091805,"remaining_time":2.665953472},
{"learn":[4.214326494],"iteration":381,"passed_time":1.661262704,"remaining_time":2.687592542},
{"learn":[4.212901398],"iteration":382,"passed_time":1.663898826,"remaining_time":2.680484532},
{"learn":[4.211331091],"iteration":383,"passed_time":1.675036555,"remaining_time":2.687037808},
{"learn":[4.208624791],"iteration":384,"passed_time":1.680390555,"remaining_time":2.684260237},
{"learn":[4.204659106],"iteration":385,"passed_time":1.685114196,"remaining_time":2.680466623},
{"learn":[4.202968852],"iteration":386,"passed_time":1.691266633,"remaining_time":2.678931385},
{"learn":[4.197261935],"iteration":387,"passed_time":1.699423005,"remaining_time":2.680533193},
{"learn":[4.196934403],"iteration":388,"passed_time":1.701924359,"remaining_time":2.673202528},
{"learn":[4.192479929],"iteration":389,"passed_time":1.706270886,"remaining_time":2.668782669},
{"learn":[4.190243116],"iteration":390,"passed_time":1.714657334,"remaining_time":2.67065554},
{"learn":[4.185852431],"iteration":391,"passed_time":1.718020074,"remaining_time":2.664684196},
{"learn":[4.180967944],"iteration":392,"passed_time":1.720821227,"remaining_time":2.657858739},
{"learn":[4.178283162],"iteration":393,"passed_time":1.727581396,"remaining_time":2.65714296},
{"learn":[4.176341157],"iteration":394,"passed_time":1.730176512,"remaining_time":2.650017189},
{"learn":[4.176041504],"iteration":395,"passed_time":1.733024087,"remaining_time":2.643299366},
{"learn":[4.175564513],"iteration":396,"passed_time":1.735015862,"remaining_time":2.635301171},
{"learn":[4.170830274],"iteration":397,"passed_time":1.737603774,"remaining_time":2.628234854},
{"learn":[4.167804808],"iteration":398,"passed_time":1.744364975,"remaining_time":2.627477068},
{"learn":[4.165860548],"iteration":399,"passed_time":1.748585891,"remaining_time":2.622878837},
{"learn":[4.160950571],"iteration":400,"passed_time":1.751642906,"remaining_time":2.616543892},
{"learn":[4.158544115],"iteration":401,"passed_time":1.75770207,"remaining_time":2.614691139},
{"learn":[4.154448767],"iteration":402,"passed_time":1.761475105,"remaining_time":2.609430863},
{"learn":[4.15197457],"iteration":403,"passed_time":1.764639161,"remaining_time":2.603279554},
{"learn":[4.149562679],"iteration":404,"passed_time":1.767527946,"remaining_time":2.596738587},
{"learn":[4.149327961],"iteration":405,"passed_time":1.773939936,"remaining_time":2.595370251},
{"learn":[4.147444889],"iteration":406,"passed_time":1.776690312,"remaining_time":2.58864215},
{"learn":[4.147254809],"iteration":407,"passed_time":1.779041701,"remaining_time":2.581354625},
{"learn":[4.144589165],"iteration":408,"passed_time":1.781466348,"remaining_time":2.574197094},
{"learn":[4.141691034],"iteration":409,"passed_time":1.7835057,"remaining_time":2.566508203},
{"learn":[4.138893468],"iteration":410,"passed_time":1.788842132,"remaining_time":2.563571814},
{"learn":[4.136964597],"iteration":411,"passed_time":1.797598391,"remaining_time":2.5655045},
{"learn":[4.133773523],"iteration":412,"passed_time":1.8034715,"remaining_time":2.56328758},
{"learn":[4.131363444],"iteration":413,"passed_time":1.805665715,"remaining_time":2.555845674},
{"learn":[4.130228592],"iteration":414,"passed_time":1.807637741,"remaining_time":2.548115851},
{"learn":[4.12884186],"iteration":415,"passed_time":1.809558847,"remaining_time":2.540342228},
{"learn":[4.12413494],"iteration":416,"passed_time":1.811609149,"remaining_time":2.532777299},
{"learn":[4.119422508],"iteration":417,"passed_time":1.815160351,"remaining_time":2.527328527},
{"learn":[4.117038244],"iteration":418,"passed_time":1.819762211,"remaining_time":2.52334569},
{"learn":[4.116067631],"iteration":419,"passed_time":1.821775522,"remaining_time":2.515785244},
{"learn":[4.110343455],"iteration":420,"passed_time":1.823723448,"remaining_time":2.508161226},
{"learn":[4.105604544],"iteration":421,"passed_time":1.825556477,"remaining_time":2.500406739},
{"learn":[4.103390131],"iteration":422,"passed_time":1.827402002,"remaining_time":2.492697293},
{"learn":[4.096724402],"iteration":423,"passed_time":1.829536398,"remaining_time":2.485407937},
{"learn":[4.093431279],"iteration":424,"passed_time":1.834317286,"remaining_time":2.481723387},
{"learn":[4.091412744],"iteration":425,"passed_time":1.836512382,"remaining_time":2.474549548},
{"learn":[4.091192901],"iteration":426,"passed_time":1.838461759,"remaining_time":2.467069292},
{"learn":[4.088994581],"iteration":427,"passed_time":1.840390559,"remaining_time":2.459587383},
{"learn":[4.087845355],"iteration":428,"passed_time":1.842310212,"remaining_time":2.452119187},
{"learn":[4.083650279],"iteration":429,"passed_time":1.844328902,"remaining_time":2.44480808},
{"learn":[4.079840652],"iteration":430,"passed_time":1.848727421,"remaining_time":2.440663347},
{"learn":[4.075707828],"iteration":431,"passed_time":1.850716938,"remaining_time":2.433350048},
{"learn":[4.071345409],"iteration":432,"passed_time":1.852594324,"remaining_time":2.425914508},
{"learn":[4.067460475],"iteration":433,"passed_time":1.854552739,"remaining_time":2.418610254},
{"learn":[4.064914749],"iteration":434,"passed_time":1.856384111,"remaining_time":2.41116557},
{"learn":[4.063823175],"iteration":435,"passed_time":1.858476294,"remaining_time":2.404084014},
{"learn":[4.058898471],"iteration":436,"passed_time":1.86234144,"remaining_time":2.399309452},
{"learn":[4.054120355],"iteration":437,"passed_time":1.864300299,"remaining_time":2.392093078},
{"learn":[4.052715901],"iteration":438,"passed_time":1.866191255,"remaining_time":2.384813882},
{"learn":[4.052114167],"iteration":439,"passed_time":1.867991568,"remaining_time":2.377443814},
{"learn":[4.051377267],"iteration":440,"passed_time":1.869977366,"remaining_time":2.370334121},
{"learn":[4.049275336],"iteration":441,"passed_time":1.872535473,"remaining_time":2.363970122},
{"learn":[4.047099198],"iteration":442,"passed_time":1.874797851,"remaining_time":2.357251474},
{"learn":[4.044348685],"iteration":443,"passed_time":1.879612073,"remaining_time":2.353748452},
{"learn":[4.042822379],"iteration":444,"passed_time":1.881670268,"remaining_time":2.346802245},
{"learn":[4.041258611],"iteration":445,"passed_time":1.883886919,"remaining_time":2.340074783},
{"learn":[4.040044254],"iteration":446,"passed_time":1.887028815,"remaining_time":2.334512158},
{"learn":[4.036860137],"iteration":447,"passed_time":1.889202015,"remaining_time":2.327766768},
{"learn":[4.036372284],"iteration":448,"passed_time":1.894159689,"remaining_time":2.324458772},
{"learn":[4.03368231],"iteration":449,"passed_time":1.896753419,"remaining_time":2.318254178},
{"learn":[4.032439519],"iteration":450,"passed_time":1.899360323,"remaining_time":2.312081634},
{"learn":[4.032008634],"iteration":451,"passed_time":1.901830576,"remaining_time":2.305759194},
{"learn":[4.030034932],"iteration":452,"passed_time":1.904431845,"remaining_time":2.299611963},
{"learn":[4.028173412],"iteration":453,"passed_time":1.90908364,"remaining_time":2.295946404},
{"learn":[4.023806097],"iteration":454,"passed_time":1.91165134,"remaining_time":2.289780177},
{"learn":[4.020239186],"iteration":455,"passed_time":1.91464304,"remaining_time":2.284135557},
{"learn":[4.017384838],"iteration":456,"passed_time":1.921061339,"remaining_time":2.282573976},
{"learn":[4.016468229],"iteration":457,"passed_time":1.924921303,"remaining_time":2.277963639},
{"learn":[4.014530169],"iteration":458,"passed_time":1.927565196,"remaining_time":2.271923249},
{"learn":[4.012884822],"iteration":459,"passed_time":1.931214221,"remaining_time":2.267077564},
{"learn":[4.008924707],"iteration":460,"passed_time":1.937281503,"remaining_time":2.265064491},
{"learn":[4.008286778],"iteration":461,"passed_time":1.940172684,"remaining_time":2.259335291},
{"learn":[4.006444202],"iteration":462,"passed_time":1.94273199,"remaining_time":2.253233432},
{"learn":[4.003284363],"iteration":463,"passed_time":1.945290611,"remaining_time":2.24714605},
{"learn":[3.999811484],"iteration":464,"passed_time":1.94791981,"remaining_time":2.24115505},
{"learn":[3.997483319],"iteration":465,"passed_time":1.954160272,"remaining_time":2.239316706},
{"learn":[3.99708333],"iteration":466,"passed_time":1.956253982,"remaining_time":2.232726708},
{"learn":[3.995860263],"iteration":467,"passed_time":1.95836503,"remaining_time":2.226175632},
{"learn":[3.994131111],"iteration":468,"passed_time":1.960320456,"remaining_time":2.219467296},
{"learn":[3.993125499],"iteration":469,"passed_time":1.962267231,"remaining_time":2.212769431},
{"learn":[3.992954084],"iteration":470,"passed_time":1.967948631,"remaining_time":2.210286254},
{"learn":[3.990635743],"iteration":471,"passed_time":1.970075209,"remaining_time":2.203812946},
{"learn":[3.986678254],"iteration":472,"passed_time":1.972117669,"remaining_time":2.197264295},
{"learn":[3.986393291],"iteration":473,"passed_time":1.974144971,"remaining_time":2.190717837},
{"learn":[3.986152671],"iteration":474,"passed_time":1.977505032,"remaining_time":2.185663456},
{"learn":[3.985596662],"iteration":475,"passed_time":1.983216583,"remaining_time":2.18320481},
{"learn":[3.983853457],"iteration":476,"passed_time":1.98700563,"remaining_time":2.178624622},
{"learn":[3.983263928],"iteration":477,"passed_time":1.991702212,"remaining_time":2.175038817},
{"learn":[3.980067202],"iteration":478,"passed_time":1.996419481,"remaining_time":2.171470876},
{"learn":[3.978115407],"iteration":479,"passed_time":2.000506071,"remaining_time":2.16721491},
{"learn":[3.972661644],"iteration":480,"passed_time":2.004546513,"remaining_time":2.162909855},
{"learn":[3.969938254],"iteration":481,"passed_time":2.006736322,"remaining_time":2.156617043},
{"learn":[3.968211434],"iteration":482,"passed_time":2.008865063,"remaining_time":2.150275854},
{"learn":[3.966113368],"iteration":483,"passed_time":2.014844436,"remaining_time":2.148057291},
{"learn":[3.962246044],"iteration":484,"passed_time":2.019155468,"remaining_time":2.144051682},
{"learn":[3.961319703],"iteration":485,"passed_time":2.021354126,"remaining_time":2.137810742},
{"learn":[3.96078191],"iteration":486,"passed_time":2.023578204,"remaining_time":2.13161318},
{"learn":[3.958913633],"iteration":487,"passed_time":2.028523426,"remaining_time":2.128286873},
{"learn":[3.957428286],"iteration":488,"passed_time":2.031140888,"remaining_time":2.12252146},
{"learn":[3.952641965],"iteration":489,"passed_time":2.033678166,"remaining_time":2.116685439},
{"learn":[3.951486786],"iteration":490,"passed_time":2.036182234,"remaining_time":2.110828426},
{"learn":[3.94938344],"iteration":491,"passed_time":2.039918283,"remaining_time":2.106257088},
{"learn":[3.947297924],"iteration":492,"passed_time":2.058070654,"remaining_time":2.116514851},
{"learn":[3.946284886],"iteration":493,"passed_time":2.060428829,"remaining_time":2.110479731},
{"learn":[3.943288204],"iteration":494,"passed_time":2.062764243,"remaining_time":2.104436248},
{"learn":[3.943076488],"iteration":495,"passed_time":2.065036939,"remaining_time":2.098343986},
{"learn":[3.942347078],"iteration":496,"passed_time":2.067344302,"remaining_time":2.092302181},
{"learn":[3.940251541],"iteration":497,"passed_time":2.0802257,"remaining_time":2.09693434},
{"learn":[3.939011019],"iteration":498,"passed_time":2.084344687,"remaining_time":2.092698774},
{"learn":[3.938760512],"iteration":499,"passed_time":2.089728048,"remaining_time":2.089728048},
{"learn":[3.934522727],"iteration":500,"passed_time":2.092155909,"remaining_time":2.083803989},
{"learn":[3.930091193],"iteration":501,"passed_time":2.094552753,"remaining_time":2.077863089},
{"learn":[3.927671752],"iteration":502,"passed_time":2.096781401,"remaining_time":2.071770092},
{"learn":[3.927280041],"iteration":503,"passed_time":2.104651855,"remaining_time":2.071244683},
{"learn":[3.925987561],"iteration":504,"passed_time":2.107419288,"remaining_time":2.065688213},
{"learn":[3.921645957],"iteration":505,"passed_time":2.109712088,"remaining_time":2.059679391},
{"learn":[3.920333743],"iteration":506,"passed_time":2.111909166,"remaining_time":2.053592147},
{"learn":[3.918659461],"iteration":507,"passed_time":2.1145528,"remaining_time":2.047952712},
{"learn":[3.916124385],"iteration":508,"passed_time":2.120542892,"remaining_time":2.045553163},
{"learn":[3.913849268],"iteration":509,"passed_time":2.123055435,"remaining_time":2.039798359},
{"learn":[3.912826119],"iteration":510,"passed_time":2.126653102,"remaining_time":2.035094651},
{"learn":[3.910034145],"iteration":511,"passed_time":2.129861232,"remaining_time":2.030023987},
{"learn":[3.90792379],"iteration":512,"passed_time":2.13552523,"remaining_time":2.027291982},
{"learn":[3.907823851],"iteration":513,"passed_time":2.138308019,"remaining_time":2.021824314},
{"learn":[3.904527401],"iteration":514,"passed_time":2.141437546,"remaining_time":2.016693612},
{"learn":[3.903378283],"iteration":515,"passed_time":2.147957007,"remaining_time":2.014750371},
{"learn":[3.902170135],"iteration":516,"passed_time":2.15150048,"remaining_time":2.010009152},
{"learn":[3.899435429],"iteration":517,"passed_time":2.154353614,"remaining_time":2.004630197},
{"learn":[3.897497505],"iteration":518,"passed_time":2.156937315,"remaining_time":1.999011269},
{"learn":[3.896426119],"iteration":519,"passed_time":2.159033666,"remaining_time":1.992954153},
{"learn":[3.896044669],"iteration":520,"passed_time":2.162141872,"remaining_time":1.987842527},
{"learn":[3.892795942],"iteration":521,"passed_time":2.168009841,"remaining_time":1.985265717},
{"learn":[3.892413888],"iteration":522,"passed_time":2.171294145,"remaining_time":1.980319899},
{"learn":[3.891738985],"iteration":523,"passed_time":2.175016123,"remaining_time":1.975778005},
{"learn":[3.88822057],"iteration":524,"passed_time":2.177871873,"remaining_time":1.970455504},
{"learn":[3.883837053],"iteration":525,"passed_time":2.179997223,"remaining_time":1.964484189},
{"learn":[3.881769742],"iteration":526,"passed_time":2.182050876,"remaining_time":1.958463121},
{"learn":[3.880356898],"iteration":527,"passed_time":2.184501565,"remaining_time":1.952812005},
{"learn":[3.879250273],"iteration":528,"passed_time":2.186269219,"remaining_time":1.946564843},
{"learn":[3.877174493],"iteration":529,"passed_time":2.189752446,"remaining_time":1.941855942},
{"learn":[3.875854201],"iteration":530,"passed_time":2.19168467,"remaining_time":1.935781752},
{"learn":[3.873189396],"iteration":531,"passed_time":2.193797459,"remaining_time":1.929881976},
{"learn":[3.871583368],"iteration":532,"passed_time":2.195730496,"remaining_time":1.923838915},
{"learn":[3.869622679],"iteration":533,"passed_time":2.197444859,"remaining_time":1.91762042},
{"learn":[3.866860164],"iteration":534,"passed_time":2.199078606,"remaining_time":1.911348695},
{"learn":[3.864498444],"iteration":535,"passed_time":2.20063269,"remaining_time":1.905025314},
{"learn":[3.861416322],"iteration":536,"passed_time":2.202655211,"remaining_time":1.89912358},
{"learn":[3.860265769],"iteration":537,"passed_time":2.205289415,"remaining_time":1.893761543},
{"learn":[3.859328725],"iteration":538,"passed_time":2.20689407,"remaining_time":1.887529066},
{"learn":[3.858521278],"iteration":539,"passed_time":2.208426889,"remaining_time":1.881252535},
{"learn":[3.85599111],"iteration":540,"passed_time":2.210103366,"remaining_time":1.875115425},
{"learn":[3.852379816],"iteration":541,"passed_time":2.211833549,"remaining_time":1.869040158},
{"learn":[3.851327537],"iteration":542,"passed_time":2.213739263,"remaining_time":1.863128625},
{"learn":[3.847854898],"iteration":543,"passed_time":2.21566826,"remaining_time":1.857251336},
{"learn":[3.847083414],"iteration":544,"passed_time":2.219829388,"remaining_time":1.853252058},
{"learn":[3.845397429],"iteration":545,"passed_time":2.222163398,"remaining_time":1.847732935},
{"learn":[3.841933528],"iteration":546,"passed_time":2.224230465,"remaining_time":1.842004389},
{"learn":[3.840996474],"iteration":547,"passed_time":2.226099357,"remaining_time":1.836125747},
{"learn":[3.838355966],"iteration":548,"passed_time":2.228144283,"remaining_time":1.830406323},
{"learn":[3.83342799],"iteration":549,"passed_time":2.230182447,"remaining_time":1.824694729},
{"learn":[3.828161535],"iteration":550,"passed_time":2.239030713,"remaining_time":1.824545899},
{"learn":[3.823502399],"iteration":551,"passed_time":2.241142847,"remaining_time":1.818898542},
{"learn":[3.820068862],"iteration":552,"passed_time":2.243127608,"remaining_time":1.813161014},
{"learn":[3.817951642],"iteration":553,"passed_time":2.244935118,"remaining_time":1.807294337},
{"learn":[3.815785958],"iteration":554,"passed_time":2.247211012,"remaining_time":1.801817838},
{"learn":[3.81503012],"iteration":555,"passed_time":2.250706018,"remaining_time":1.797326388},
{"learn":[3.813529315],"iteration":556,"passed_time":2.254454149,"remaining_time":1.793039835},
{"learn":[3.808881326],"iteration":557,"passed_time":2.256147244,"remaining_time":1.787127387},
{"learn":[3.808740434],"iteration":558,"passed_time":2.257684482,"remaining_time":1.781107078},
{"learn":[3.80714352],"iteration":559,"passed_time":2.25935858,"remaining_time":1.775210312},
{"learn":[3.80573346],"iteration":560,"passed_time":2.260950867,"remaining_time":1.769264582},
{"learn":[3.803370052],"iteration":561,"passed_time":2.26862991,"remaining_time":1.768078115},
{"learn":[3.803215211],"iteration":562,"passed_time":2.270637754,"remaining_time":1.762466605},
{"learn":[3.801309667],"iteration":563,"passed_time":2.272693666,"remaining_time":1.756905032},
{"learn":[3.800003847],"iteration":564,"passed_time":2.274389365,"remaining_time":1.751078537},
{"learn":[3.798026138],"iteration":565,"passed_time":2.276332653,"remaining_time":1.745456487},
{"learn":[3.794745847],"iteration":566,"passed_time":2.282041901,"remaining_time":1.742723356},
{"learn":[3.794312041],"iteration":567,"passed_time":2.283850205,"remaining_time":1.737012832},
{"learn":[3.792205926],"iteration":568,"passed_time":2.28582877,"remaining_time":1.731444991},
{"learn":[3.788991061],"iteration":569,"passed_time":2.28777051,"remaining_time":1.725861964},
{"learn":[3.787391572],"iteration":570,"passed_time":2.289639664,"remaining_time":1.720237156},
{"learn":[3.7826445],"iteration":571,"passed_time":2.291374293,"remaining_time":1.714524821},
{"learn":[3.781700331],"iteration":572,"passed_time":2.295144434,"remaining_time":1.710343234},
{"learn":[3.780045374],"iteration":573,"passed_time":2.29689808,"remaining_time":1.704666519},
{"learn":[3.775462644],"iteration":574,"passed_time":2.29852606,"remaining_time":1.698910566},
{"learn":[3.773711943],"iteration":575,"passed_time":2.300125632,"remaining_time":1.693148035},
{"learn":[3.772415806],"iteration":576,"passed_time":2.301745631,"remaining_time":1.687414908},
{"learn":[3.770170875],"iteration":577,"passed_time":2.303396658,"remaining_time":1.681718667},
{"learn":[3.765166479],"iteration":578,"passed_time":2.30511032,"remaining_time":1.676081943},
{"learn":[3.763976102],"iteration":579,"passed_time":2.308994859,"remaining_time":1.67203076},
{"learn":[3.760761708],"iteration":580,"passed_time":2.310731712,"remaining_time":1.666431304},
{"learn":[3.758155662],"iteration":581,"passed_time":2.312318536,"remaining_time":1.660737368},
{"learn":[3.756844548],"iteration":582,"passed_time":2.314234773,"remaining_time":1.65529314},
{"learn":[3.753098923],"iteration":583,"passed_time":2.315918935,"remaining_time":1.64969568},
{"learn":[3.751618946],"iteration":584,"passed_time":2.317588329,"remaining_time":1.644101122},
{"learn":[3.751398464],"iteration":585,"passed_time":2.319535459,"remaining_time":1.638716177},
{"learn":[3.749920103],"iteration":586,"passed_time":2.321370631,"remaining_time":1.633264175},
{"learn":[3.748237465],"iteration":587,"passed_time":2.324288194,"remaining_time":1.628582884},
{"learn":[3.746021536],"iteration":588,"passed_time":2.32591682,"remaining_time":1.623008171},
{"learn":[3.74417648],"iteration":589,"passed_time":2.32753151,"remaining_time":1.617437151},
{"learn":[3.738788389],"iteration":590,"passed_time":2.329244565,"remaining_time":1.611947592},
{"learn":[3.736021611],"iteration":591,"passed_time":2.330981074,"remaining_time":1.606486956},
{"learn":[3.734546151],"iteration":592,"passed_time":2.332902018,"remaining_time":1.601165466},
{"learn":[3.733527479],"iteration":593,"passed_time":2.33449443,"remaining_time":1.595630873},
{"learn":[3.733026392],"iteration":594,"passed_time":2.33731699,"remaining_time":1.590946859},
{"learn":[3.730314752],"iteration":595,"passed_time":2.339318562,"remaining_time":1.585712582},
{"learn":[3.727342596],"iteration":596,"passed_time":2.341109884,"remaining_time":1.580347208},
{"learn":[3.725459604],"iteration":597,"passed_time":2.34291004,"remaining_time":1.574999726},
{"learn":[3.723158842],"iteration":598,"passed_time":2.344731466,"remaining_time":1.569678327},
{"learn":[3.722362756],"iteration":599,"passed_time":2.34645038,"remaining_time":1.564300253},
{"learn":[3.721443615],"iteration":600,"passed_time":2.348247718,"remaining_time":1.558986422},
{"learn":[3.720743486],"iteration":601,"passed_time":2.349915245,"remaining_time":1.553598451},
{"learn":[3.720215334],"iteration":602,"passed_time":2.352917825,"remaining_time":1.549101785},
{"learn":[3.719436563],"iteration":603,"passed_time":2.354568738,"remaining_time":1.543723875},
{"learn":[3.715046574],"iteration":604,"passed_time":2.35626272,"remaining_time":1.538386404},
{"learn":[3.71443396],"iteration":605,"passed_time":2.357927961,"remaining_time":1.533042272},
{"learn":[3.712938941],"iteration":606,"passed_time":2.359652007,"remaining_time":1.527748334},
{"learn":[3.712814764],"iteration":607,"passed_time":2.361360614,"remaining_time":1.522456185},
{"learn":[3.71235348],"iteration":608,"passed_time":2.363045268,"remaining_time":1.517160426},
{"learn":[3.711223749],"iteration":609,"passed_time":2.365019346,"remaining_time":1.512061549},
{"learn":[3.710755648],"iteration":610,"passed_time":2.367847103,"remaining_time":1.507516404},
{"learn":[3.708668039],"iteration":611,"passed_time":2.369523825,"remaining_time":1.502247131},
{"learn":[3.705623591],"iteration":612,"passed_time":2.371176886,"remaining_time":1.496974641},
{"learn":[3.704045802],"iteration":613,"passed_time":2.37287449,"remaining_time":1.491741943},
{"learn":[3.699915209],"iteration":614,"passed_time":2.374522084,"remaining_time":1.486489435},
{"learn":[3.696182221],"iteration":615,"passed_time":2.376177652,"remaining_time":1.481253601},
{"learn":[3.694263278],"iteration":616,"passed_time":2.377719756,"remaining_time":1.475958941},
{"learn":[3.693810229],"iteration":617,"passed_time":2.379645961,"remaining_time":1.470913847},
{"learn":[3.690900932],"iteration":618,"passed_time":2.382283148,"remaining_time":1.466316445},
{"learn":[3.688020895],"iteration":619,"passed_time":2.383856992,"remaining_time":1.46107364},
{"learn":[3.685491894],"iteration":620,"passed_time":2.385436712,"remaining_time":1.455846238},
{"learn":[3.684328128],"iteration":621,"passed_time":2.387250312,"remaining_time":1.450772698},
{"learn":[3.680640153],"iteration":622,"passed_time":2.388910821,"remaining_time":1.445616982},
{"learn":[3.678932783],"iteration":623,"passed_time":2.390483285,"remaining_time":1.440419415},
{"learn":[3.674167041],"iteration":624,"passed_time":2.392072211,"remaining_time":1.435243326},
{"learn":[3.672200976],"iteration":625,"passed_time":2.393812802,"remaining_time":1.43016931},
{"learn":[3.670606604],"iteration":626,"passed_time":2.396047706,"remaining_time":1.425399991},
{"learn":[3.665506042],"iteration":627,"passed_time":2.39773964,"remaining_time":1.420317112},
{"learn":[3.664214007],"iteration":628,"passed_time":2.399563824,"remaining_time":1.415323019},
{"learn":[3.66261643],"iteration":629,"passed_time":2.401437205,"remaining_time":1.410367882},
{"learn":[3.662118449],"iteration":630,"passed_time":2.402996787,"remaining_time":1.405239009},
{"learn":[3.660871366],"iteration":631,"passed_time":2.404723519,"remaining_time":1.400218758},
{"learn":[3.656695243],"iteration":632,"passed_time":2.406381737,"remaining_time":1.39516919},
{"learn":[3.654497801],"iteration":633,"passed_time":2.409956367,"remaining_time":1.391236641},
{"learn":[3.654189134],"iteration":634,"passed_time":2.411711316,"remaining_time":1.386259261},
{"learn":[3.653957699],"iteration":635,"passed_time":2.413379122,"remaining_time":1.381242139},
{"learn":[3.651920725],"iteration":636,"passed_time":2.414954048,"remaining_time":1.376182605},
{"learn":[3.65106705],"iteration":637,"passed_time":2.416487169,"remaining_time":1.371110274},
{"learn":[3.650612844],"iteration":638,"passed_time":2.418106026,"remaining_time":1.366097457},
{"learn":[3.649884732],"iteration":639,"passed_time":2.419700515,"remaining_time":1.36108154},
{"learn":[3.646276182],"iteration":640,"passed_time":2.421285451,"remaining_time":1.356070947},
{"learn":[3.645808194],"iteration":641,"passed_time":2.425177689,"remaining_time":1.352357652},
{"learn":[3.645042989],"iteration":642,"passed_time":2.426792637,"remaining_time":1.347379426},
{"learn":[3.639864499],"iteration":643,"passed_time":2.428368641,"remaining_time":1.342390118},
{"learn":[3.637318478],"iteration":644,"passed_time":2.430037379,"remaining_time":1.337462433},
{"learn":[3.636344905],"iteration":645,"passed_time":2.431565933,"remaining_time":1.332468019},
{"learn":[3.634754643],"iteration":646,"passed_time":2.433125358,"remaining_time":1.327501161},
{"learn":[3.630724975],"iteration":647,"passed_time":2.434717697,"remaining_time":1.3225627},
{"learn":[3.629408252],"iteration":648,"passed_time":2.436381782,"remaining_time":1.317673352},
{"learn":[3.62790646],"iteration":649,"passed_time":2.43967991,"remaining_time":1.313673798},
{"learn":[3.627388973],"iteration":650,"passed_time":2.441662497,"remaining_time":1.308971139},
{"learn":[3.625163557],"iteration":651,"passed_time":2.443445816,"remaining_time":1.304170466},
{"learn":[3.623701985],"iteration":652,"passed_time":2.44558353,"remaining_time":1.299567358},
{"learn":[3.622342639],"iteration":653,"passed_time":2.447181246,"remaining_time":1.294686103},
{"learn":[3.621130639],"iteration":654,"passed_time":2.448854109,"remaining_time":1.289854454},
{"learn":[3.619125665],"iteration":655,"passed_time":2.450497384,"remaining_time":1.285016921},
{"learn":[3.618878783],"iteration":656,"passed_time":2.454924717,"remaining_time":1.281642585},
{"learn":[3.616207429],"iteration":657,"passed_time":2.456879971,"remaining_time":1.276980167},
{"learn":[3.61206486],"iteration":658,"passed_time":2.458675458,"remaining_time":1.272243295},
{"learn":[3.611955873],"iteration":659,"passed_time":2.460442939,"remaining_time":1.267500908},
{"learn":[3.610713743],"iteration":660,"passed_time":2.462621713,"remaining_time":1.262978458},
{"learn":[3.610044025],"iteration":661,"passed_time":2.464391259,"remaining_time":1.258254148},
{"learn":[3.607342669],"iteration":662,"passed_time":2.466464562,"remaining_time":1.253693148},
{"learn":[3.602510618],"iteration":663,"passed_time":2.470076569,"remaining_time":1.249918264},
{"learn":[3.600492392],"iteration":664,"passed_time":2.472269484,"remaining_time":1.245428988},
{"learn":[3.597171065],"iteration":665,"passed_time":2.474042353,"remaining_time":1.240735955},
{"learn":[3.594358798],"iteration":666,"passed_time":2.475683525,"remaining_time":1.235985928},
{"learn":[3.593945251],"iteration":667,"passed_time":2.477237305,"remaining_time":1.231201774},
{"learn":[3.593607748],"iteration":668,"passed_time":2.478867642,"remaining_time":1.226465156},
{"learn":[3.592238714],"iteration":669,"passed_time":2.482514259,"remaining_time":1.222730904},
{"learn":[3.590144654],"iteration":670,"passed_time":2.484439209,"remaining_time":1.218152757},
{"learn":[3.587151536],"iteration":671,"passed_time":2.486182018,"remaining_time":1.213493604},
{"learn":[3.586070865],"iteration":672,"passed_time":2.487982905,"remaining_time":1.208871337},
{"learn":[3.585102746],"iteration":673,"passed_time":2.489799554,"remaining_time":1.204265066},
{"learn":[3.584362847],"iteration":674,"passed_time":2.493453781,"remaining_time":1.20055182},
{"learn":[3.581407561],"iteration":675,"passed_time":2.496943513,"remaining_time":1.196759909},
{"learn":[3.57919422],"iteration":676,"passed_time":2.499768124,"remaining_time":1.192651557},
{"learn":[3.577632204],"iteration":677,"passed_time":2.501482046,"remaining_time":1.188019497},
{"learn":[3.573911195],"iteration":678,"passed_time":2.503048204,"remaining_time":1.183326176},
{"learn":[3.573408216],"iteration":679,"passed_time":2.504626742,"remaining_time":1.178647879},
{"learn":[3.571076482],"iteration":680,"passed_time":2.506202002,"remaining_time":1.173977149},
{"learn":[3.568177107],"iteration":681,"passed_time":2.508043233,"remaining_time":1.169439513},
{"learn":[3.564824621],"iteration":682,"passed_time":2.512498045,"remaining_time":1.166122812},
{"learn":[3.562475026],"iteration":683,"passed_time":2.514317706,"remaining_time":1.161585373},
{"learn":[3.561226889],"iteration":684,"passed_time":2.515959914,"remaining_time":1.156974267},
{"learn":[3.559383467],"iteration":685,"passed_time":2.517541322,"remaining_time":1.152343987},
{"learn":[3.555209766],"iteration":686,"passed_time":2.519251447,"remaining_time":1.147781227},
{"learn":[3.55345383],"iteration":687,"passed_time":2.521129813,"remaining_time":1.143303055},
{"learn":[3.552300968],"iteration":688,"passed_time":2.522771001,"remaining_time":1.138725372},
{"learn":[3.551253986],"iteration":689,"passed_time":2.52649578,"remaining_time":1.135092307},
{"learn":[3.549807725],"iteration":690,"passed_time":2.528614501,"remaining_time":1.130740783},
{"learn":[3.547992926],"iteration":691,"passed_time":2.530387361,"remaining_time":1.126241774},
{"learn":[3.545438607],"iteration":692,"passed_time":2.532224945,"remaining_time":1.121779305},
{"learn":[3.543313763],"iteration":693,"passed_time":2.533790786,"remaining_time":1.117204583},
{"learn":[3.542962896],"iteration":694,"passed_time":2.535428435,"remaining_time":1.112670033},
{"learn":[3.539800465],"iteration":695,"passed_time":2.537101499,"remaining_time":1.108159276},
{"learn":[3.53953187],"iteration":696,"passed_time":2.539135643,"remaining_time":1.10381363},
{"learn":[3.536332425],"iteration":697,"passed_time":2.541374082,"remaining_time":1.099562998},
{"learn":[3.534993327],"iteration":698,"passed_time":2.543039259,"remaining_time":1.095071269},
{"learn":[3.531637011],"iteration":699,"passed_time":2.544779067,"remaining_time":1.0906196},
{"learn":[3.531040284],"iteration":700,"passed_time":2.546359318,"remaining_time":1.086107612},
{"learn":[3.529973872],"iteration":701,"passed_time":2.548000327,"remaining_time":1.081629769},
{"learn":[3.527325183],"iteration":702,"passed_time":2.549636517,"remaining_time":1.07715796},
{"learn":[3.527200815],"iteration":703,"passed_time":2.551275975,"remaining_time":1.07269558},
{"learn":[3.523459911],"iteration":704,"passed_time":2.554742574,"remaining_time":1.069005758},
{"learn":[3.522729934],"iteration":705,"passed_time":2.556308912,"remaining_time":1.064525241},
{"learn":[3.522260582],"iteration":706,"passed_time":2.557935929,"remaining_time":1.060078115},
{"learn":[3.518641591],"iteration":707,"passed_time":2.5595584,"remaining_time":1.05563708},
{"learn":[3.516856405],"iteration":708,"passed_time":2.561386951,"remaining_time":1.051288579},
{"learn":[3.515083413],"iteration":709,"passed_time":2.563049878,"remaining_time":1.046879528},
{"learn":[3.514671214],"iteration":710,"passed_time":2.564633033,"remaining_time":1.042445776},
{"learn":[3.512617621],"iteration":711,"passed_time":2.566339531,"remaining_time":1.038069923},
{"learn":[3.510747971],"iteration":712,"passed_time":2.570008415,"remaining_time":1.034491466},
{"learn":[3.508149266],"iteration":713,"passed_time":2.571904956,"remaining_time":1.030202826},
{"learn":[3.504557165],"iteration":714,"passed_time":2.573467788,"remaining_time":1.02578786},
{"learn":[3.501367208],"iteration":715,"passed_time":2.57509404,"remaining_time":1.021406016},
{"learn":[3.497593362],"iteration":716,"passed_time":2.576855807,"remaining_time":1.017085347},
{"learn":[3.496291169],"iteration":717,"passed_time":2.578423439,"remaining_time":1.012695557},
{"learn":[3.49330374],"iteration":718,"passed_time":2.580063482,"remaining_time":1.008341917},
{"learn":[3.490044385],"iteration":719,"passed_time":2.581998305,"remaining_time":1.004110452},
{"learn":[3.488891789],"iteration":720,"passed_time":2.584847388,"remaining_time":1.000239142},
{"learn":[3.486869081],"iteration":721,"passed_time":2.586484424,"remaining_time":0.995903975},
{"learn":[3.486303638],"iteration":722,"passed_time":2.587978156,"remaining_time":0.9915213683},
{"learn":[3.486035862],"iteration":723,"passed_time":2.589593419,"remaining_time":0.9871930715},
{"learn":[3.482668951],"iteration":724,"passed_time":2.59124278,"remaining_time":0.9828851923},
{"learn":[3.47820549],"iteration":725,"passed_time":2.592864489,"remaining_time":0.9785742013},
{"learn":[3.474392283],"iteration":726,"passed_time":2.594412662,"remaining_time":0.974242994},
{"learn":[3.472268163],"iteration":727,"passed_time":2.596397988,"remaining_time":0.9700827649},
{"learn":[3.471209164],"iteration":728,"passed_time":2.599266507,"remaining_time":0.9662568222},
{"learn":[3.470049971],"iteration":729,"passed_time":2.60098374,"remaining_time":0.9620076845},
{"learn":[3.469078654],"iteration":730,"passed_time":2.602542983,"remaining_time":0.9577073356},
{"learn":[3.468643292],"iteration":731,"passed_time":2.604370812,"remaining_time":0.9535128111},
{"learn":[3.468134848],"iteration":732,"passed_time":2.605940017,"remaining_time":0.9492305381},
{"learn":[3.467820182],"iteration":733,"passed_time":2.60742349,"remaining_time":0.944924589},
{"learn":[3.465776156],"iteration":734,"passed_time":2.609108035,"remaining_time":0.9406988155},
{"learn":[3.463037608],"iteration":735,"passed_time":2.610804844,"remaining_time":0.9364843462},
{"learn":[3.45965637],"iteration":736,"passed_time":2.612892992,"remaining_time":0.9324163593},
{"learn":[3.457275091],"iteration":737,"passed_time":2.6145686,"remaining_time":0.9282072806},
{"learn":[3.455522955],"iteration":738,"passed_time":2.616174915,"remaining_time":0.9239805858},
{"learn":[3.451270508],"iteration":739,"passed_time":2.617697064,"remaining_time":0.9197314007},
{"learn":[3.450978947],"iteration":740,"passed_time":2.619266491,"remaining_time":0.9155061016},
{"learn":[3.450608492],"iteration":741,"passed_time":2.620853662,"remaining_time":0.9112941303},
{"learn":[3.448122004],"iteration":742,"passed_time":2.622511803,"remaining_time":0.9071137732},
{"learn":[3.445646714],"iteration":743,"passed_time":2.625260619,"remaining_time":0.9033154818},
{"learn":[3.44411263],"iteration":744,"passed_time":2.627481091,"remaining_time":0.8993391653},
{"learn":[3.443264164],"iteration":745,"passed_time":2.62946648,"remaining_time":0.8952875145},
{"learn":[3.439521363],"iteration":746,"passed_time":2.631393589,"remaining_time":0.8912216572},
{"learn":[3.436809225],"iteration":747,"passed_time":2.633153368,"remaining_time":0.8871051454},
{"learn":[3.435509465],"iteration":748,"passed_time":2.634837019,"remaining_time":0.8829694149},
{"learn":[3.434450277],"iteration":749,"passed_time":2.636475503,"remaining_time":0.8788251675},
{"learn":[3.431786753],"iteration":750,"passed_time":2.638117511,"remaining_time":0.8746887619},
{"learn":[3.430150302],"iteration":751,"passed_time":2.641588798,"remaining_time":0.871162263},
{"learn":[3.42696281],"iteration":752,"passed_time":2.643185002,"remaining_time":0.8670208441},
{"learn":[3.426870334],"iteration":753,"passed_time":2.644712955,"remaining_time":0.8628639085},
{"learn":[3.425200309],"iteration":754,"passed_time":2.646388266,"remaining_time":0.8587617551},
{"learn":[3.423383783],"iteration":755,"passed_time":2.647945373,"remaining_time":0.8546278718},
{"learn":[3.422752979],"iteration":756,"passed_time":2.649458983,"remaining_time":0.8504868333},
{"learn":[3.420845924],"iteration":757,"passed_time":2.650995183,"remaining_time":0.8463599398},
{"learn":[3.418917862],"iteration":758,"passed_time":2.652626989,"remaining_time":0.8422702298},
{"learn":[3.417095735],"iteration":759,"passed_time":2.656065089,"remaining_time":0.8387573966},
{"learn":[3.414391848],"iteration":760,"passed_time":2.657784345,"remaining_time":0.8347049389},
{"learn":[3.41426711],"iteration":761,"passed_time":2.659309857,"remaining_time":0.8305980918},
{"learn":[3.411976013],"iteration":762,"passed_time":2.660930934,"remaining_time":0.826527695},
{"learn":[3.408614844],"iteration":763,"passed_time":2.662519448,"remaining_time":0.8224536514},
{"learn":[3.407906721],"iteration":764,"passed_time":2.664152517,"remaining_time":0.8183997929},
{"learn":[3.407494015],"iteration":765,"passed_time":2.665790313,"remaining_time":0.8143536988},
{"learn":[3.406287128],"iteration":766,"passed_time":2.66738915,"remaining_time":0.8103020493},
{"learn":[3.404600442],"iteration":767,"passed_time":2.670956693,"remaining_time":0.8068515011},
{"learn":[3.404012662],"iteration":768,"passed_time":2.672509786,"remaining_time":0.8027955274},
{"learn":[3.400398762],"iteration":769,"passed_time":2.674158923,"remaining_time":0.7987747431},
{"learn":[3.399737714],"iteration":770,"passed_time":2.675818957,"remaining_time":0.7947633478},
{"learn":[3.399185251],"iteration":771,"passed_time":2.67744116,"remaining_time":0.7907468712},
{"learn":[3.397245411],"iteration":772,"passed_time":2.679096562,"remaining_time":0.7867463383},
{"learn":[3.396229831],"iteration":773,"passed_time":2.680722293,"remaining_time":0.7827432018},
{"learn":[3.394002836],"iteration":774,"passed_time":2.682434572,"remaining_time":0.7787713274},
{"learn":[3.389617243],"iteration":775,"passed_time":2.685805233,"remaining_time":0.7752839848},
{"learn":[3.385426488],"iteration":776,"passed_time":2.687406126,"remaining_time":0.7712890169},
{"learn":[3.385072258],"iteration":777,"passed_time":2.688992974,"remaining_time":0.7672961956},
{"learn":[3.383842366],"iteration":778,"passed_time":2.690613983,"remaining_time":0.7633192429},
{"learn":[3.380110746],"iteration":779,"passed_time":2.692334091,"remaining_time":0.7593762821},
{"learn":[3.378595218],"iteration":780,"passed_time":2.693919957,"remaining_time":0.7554013709},
{"learn":[3.377371219],"iteration":781,"passed_time":2.695509858,"remaining_time":0.7514336944},
{"learn":[3.375814782],"iteration":782,"passed_time":2.697149981,"remaining_time":0.74748601},
{"learn":[3.374195887],"iteration":783,"passed_time":2.701220225,"remaining_time":0.7442137355},
{"learn":[3.373704309],"iteration":784,"passed_time":2.702947124,"remaining_time":0.74029762},
{"learn":[3.372971757],"iteration":785,"passed_time":2.704515079,"remaining_time":0.7363438002},
{"learn":[3.371565136],"iteration":786,"passed_time":2.706149601,"remaining_time":0.7324140596},
{"learn":[3.3700309],"iteration":787,"passed_time":2.707816332,"remaining_time":0.7284988101},
{"learn":[3.368186663],"iteration":788,"passed_time":2.709666511,"remaining_time":0.7246383192},
{"learn":[3.366710398],"iteration":789,"passed_time":2.711374903,"remaining_time":0.7207452274},
{"learn":[3.364598042],"iteration":790,"passed_time":2.714609732,"remaining_time":0.7172609784},
{"learn":[3.36348442],"iteration":791,"passed_time":2.716742781,"remaining_time":0.713488003},
{"learn":[3.362001759],"iteration":792,"passed_time":2.718602063,"remaining_time":0.7096477012},
{"learn":[3.361580401],"iteration":793,"passed_time":2.720480129,"remaining_time":0.7058172627},
{"learn":[3.359543675],"iteration":794,"passed_time":2.722046713,"remaining_time":0.7019114165},
{"learn":[3.35766119],"iteration":795,"passed_time":2.723591961,"remaining_time":0.6980059799},
{"learn":[3.354592969],"iteration":796,"passed_time":2.725286908,"remaining_time":0.6941445952},
{"learn":[3.350985986],"iteration":797,"passed_time":2.726907423,"remaining_time":0.6902697988},
{"learn":[3.349589624],"iteration":798,"passed_time":2.730220903,"remaining_time":0.686826535},
{"learn":[3.349110856],"iteration":799,"passed_time":2.731913886,"remaining_time":0.6829784715},
{"learn":[3.345315441],"iteration":800,"passed_time":2.733533119,"remaining_time":0.6791174664},
{"learn":[3.34397474],"iteration":801,"passed_time":2.735124958,"remaining_time":0.6752552889},
{"learn":[3.343800902],"iteration":802,"passed_time":2.736622186,"remaining_time":0.6713755549},
{"learn":[3.342329465],"iteration":803,"passed_time":2.738187541,"remaining_time":0.6675183559},
{"learn":[3.34220347],"iteration":804,"passed_time":2.739680225,"remaining_time":0.663649247},
{"learn":[3.341279219],"iteration":805,"passed_time":2.741799153,"remaining_time":0.6599367688},
{"learn":[3.337329521],"iteration":806,"passed_time":2.744861212,"remaining_time":0.6564537967},
{"learn":[3.336708453],"iteration":807,"passed_time":2.746437261,"remaining_time":0.652618755},
{"learn":[3.333252703],"iteration":808,"passed_time":2.748075502,"remaining_time":0.6488039812},
{"learn":[3.332186769],"iteration":809,"passed_time":2.749734595,"remaining_time":0.6449994729},
{"learn":[3.330594851],"iteration":810,"passed_time":2.751368808,"remaining_time":0.6411944572},
{"learn":[3.327867442],"iteration":811,"passed_time":2.75293006,"remaining_time":0.6373778957},
{"learn":[3.327563111],"iteration":812,"passed_time":2.754569548,"remaining_time":0.6335848776},
{"learn":[3.326308994],"iteration":813,"passed_time":2.756163369,"remaining_time":0.6297867158},
{"learn":[3.326249879],"iteration":814,"passed_time":2.759831445,"remaining_time":0.6264648065},
{"learn":[3.322336238],"iteration":815,"passed_time":2.762047747,"remaining_time":0.6228146881},
{"learn":[3.320491154],"iteration":816,"passed_time":2.76362391,"remaining_time":0.6190246946},
{"learn":[3.320434271],"iteration":817,"passed_time":2.765190557,"remaining_time":0.6152379967},
{"learn":[3.319609638],"iteration":818,"passed_time":2.766915172,"remaining_time":0.6114916314},
{"learn":[3.316182682],"iteration":819,"passed_time":2.768549689,"remaining_time":0.6077304195},
{"learn":[3.313126612],"iteration":820,"passed_time":2.770269843,"remaining_time":0.6039930596},
{"learn":[3.311222803],"iteration":821,"passed_time":2.773760503,"remaining_time":0.6006440018},
{"learn":[3.309627335],"iteration":822,"passed_time":2.775967136,"remaining_time":0.5970184485},
{"learn":[3.307974895],"iteration":823,"passed_time":2.777936865,"remaining_time":0.5933457382},
{"learn":[3.307321505],"iteration":824,"passed_time":2.779813975,"remaining_time":0.5896575099},
{"learn":[3.306759087],"iteration":825,"passed_time":2.781647203,"remaining_time":0.5859644229},
{"learn":[3.30484037],"iteration":826,"passed_time":2.783596398,"remaining_time":0.582300093},
{"learn":[3.30201994],"iteration":827,"passed_time":2.793280298,"remaining_time":0.580246632},
{"learn":[3.299302297],"iteration":828,"passed_time":2.795305454,"remaining_time":0.5765949731},
{"learn":[3.298132671],"iteration":829,"passed_time":2.797121491,"remaining_time":0.5729044017},
{"learn":[3.296976183],"iteration":830,"passed_time":2.799007736,"remaining_time":0.5692326202},
{"learn":[3.293144745],"iteration":831,"passed_time":2.800782183,"remaining_time":0.5655425561},
{"learn":[3.290284404],"iteration":832,"passed_time":2.805073084,"remaining_time":0.5623615906},
{"learn":[3.288285745],"iteration":833,"passed_time":2.807583552,"remaining_time":0.5588235847},
{"learn":[3.286662667],"iteration":834,"passed_time":2.809226323,"remaining_time":0.5551165788},
{"learn":[3.285692682],"iteration":835,"passed_time":2.810930303,"remaining_time":0.5514265188},
{"learn":[3.284565611],"iteration":836,"passed_time":2.812585483,"remaining_time":0.5477317009},
{"learn":[3.283897383],"iteration":837,"passed_time":2.81420476,"remaining_time":0.5440348103},
{"learn":[3.280712855],"iteration":838,"passed_time":2.815848042,"remaining_time":0.5403474789},
{"learn":[3.280468341],"iteration":839,"passed_time":2.821552331,"remaining_time":0.5374385392},
{"learn":[3.277814895],"iteration":840,"passed_time":2.82390023,"remaining_time":0.5338883906},
{"learn":[3.276316385],"iteration":841,"passed_time":2.825499804,"remaining_time":0.5302006758},
{"learn":[3.27557063],"iteration":842,"passed_time":2.827414505,"remaining_time":0.5265766041},
{"learn":[3.27499628],"iteration":843,"passed_time":2.829064222,"remaining_time":0.5229076049},
{"learn":[3.273569958],"iteration":844,"passed_time":2.830663324,"remaining_time":0.5192341008},
{"learn":[3.269665595],"iteration":845,"passed_time":2.83611413,"remaining_time":0.5162666384},
{"learn":[3.267984685],"iteration":846,"passed_time":2.837868183,"remaining_time":0.5126255396},
{"learn":[3.267702508],"iteration":847,"passed_time":2.839425576,"remaining_time":0.508953641},
{"learn":[3.266671924],"iteration":848,"passed_time":2.841068302,"remaining_time":0.5053019005},
{"learn":[3.265359825],"iteration":849,"passed_time":2.842761209,"remaining_time":0.5016637427},
{"learn":[3.2618983],"iteration":850,"passed_time":2.844368732,"remaining_time":0.4980152069},
{"learn":[3.260456253],"iteration":851,"passed_time":2.846092653,"remaining_time":0.4943916816},
{"learn":[3.258389147],"iteration":852,"passed_time":2.849729712,"remaining_time":0.4911023068},
{"learn":[3.258108469],"iteration":853,"passed_time":2.851298973,"remaining_time":0.4874586066},
{"learn":[3.256424936],"iteration":854,"passed_time":2.852893819,"remaining_time":0.483824098},
{"learn":[3.254817983],"iteration":855,"passed_time":2.854698286,"remaining_time":0.4802296182},
{"learn":[3.253898449],"iteration":856,"passed_time":2.856492544,"remaining_time":0.4766376124},
{"learn":[3.253023652],"iteration":857,"passed_time":2.858155664,"remaining_time":0.4730280935},
{"learn":[3.252845542],"iteration":858,"passed_time":2.859853188,"remaining_time":0.4694287539},
{"learn":[3.252316026],"iteration":859,"passed_time":2.863959716,"remaining_time":0.4662260002},
{"learn":[3.24975301],"iteration":860,"passed_time":2.865641179,"remaining_time":0.4626296444},
{"learn":[3.249151075],"iteration":861,"passed_time":2.867247043,"remaining_time":0.4590256286},
{"learn":[3.246257135],"iteration":862,"passed_time":2.868825775,"remaining_time":0.4554219365},
{"learn":[3.243826471],"iteration":863,"passed_time":2.870564037,"remaining_time":0.4518480429},
{"learn":[3.243190653],"iteration":864,"passed_time":2.872483054,"remaining_time":0.4483066038},
{"learn":[3.24008797],"iteration":865,"passed_time":2.874332743,"remaining_time":0.4447581842},
{"learn":[3.240036811],"iteration":866,"passed_time":2.877283486,"remaining_time":0.4413825877},
{"learn":[3.238676314],"iteration":867,"passed_time":2.879086527,"remaining_time":0.437833435},
{"learn":[3.237848782],"iteration":868,"passed_time":2.880760046,"remaining_time":0.4342687756},
{"learn":[3.236405498],"iteration":869,"passed_time":2.882381042,"remaining_time":0.4307006155},
{"learn":[3.233378068],"iteration":870,"passed_time":2.884305406,"remaining_time":0.427181857},
{"learn":[3.233169169],"iteration":871,"passed_time":2.885920432,"remaining_time":0.4236213478},
{"learn":[3.232434885],"iteration":872,"passed_time":2.88744358,"remaining_time":0.4200519298},
{"learn":[3.229978115],"iteration":873,"passed_time":2.889147242,"remaining_time":0.416513218},
{"learn":[3.229648848],"iteration":874,"passed_time":2.892417819,"remaining_time":0.4132025455},
{"learn":[3.227208761],"iteration":875,"passed_time":2.894295338,"remaining_time":0.4096947739},
{"learn":[3.226258869],"iteration":876,"passed_time":2.896043028,"remaining_time":0.4061725113},
{"learn":[3.225331995],"iteration":877,"passed_time":2.8979868,"remaining_time":0.4026815371},
{"learn":[3.221968268],"iteration":878,"passed_time":2.899889687,"remaining_time":0.3991884552},
{"learn":[3.221166317],"iteration":879,"passed_time":2.901654955,"remaining_time":0.3956802212},
{"learn":[3.220047503],"iteration":880,"passed_time":2.903326947,"remaining_time":0.3921633448},
{"learn":[3.21982781],"iteration":881,"passed_time":2.905222215,"remaining_time":0.3886805232},
{"learn":[3.216693405],"iteration":882,"passed_time":2.908105539,"remaining_time":0.3853322175},
{"learn":[3.214798761],"iteration":883,"passed_time":2.909739554,"remaining_time":0.3818210275},
{"learn":[3.214395085],"iteration":884,"passed_time":2.911358962,"remaining_time":0.3783121815},
{"learn":[3.213470696],"iteration":885,"passed_time":2.913099421,"remaining_time":0.374823176},
{"learn":[3.211595017],"iteration":886,"passed_time":2.914682934,"remaining_time":0.371318119},
{"learn":[3.210965255],"iteration":887,"passed_time":2.916248372,"remaining_time":0.36781511},
{"learn":[3.209413583],"iteration":888,"passed_time":2.917824577,"remaining_time":0.3643178043},
{"learn":[3.208331683],"iteration":889,"passed_time":2.919598043,"remaining_time":0.3608491963},
{"learn":[3.207110711],"iteration":890,"passed_time":2.922718991,"remaining_time":0.3575492369},
{"learn":[3.204519413],"iteration":891,"passed_time":2.924312936,"remaining_time":0.354064795},
{"learn":[3.201421296],"iteration":892,"passed_time":2.925918102,"remaining_time":0.3505859316},
{"learn":[3.200691259],"iteration":893,"passed_time":2.927473423,"remaining_time":0.3471053499},
{"learn":[3.200485067],"iteration":894,"passed_time":2.928988794,"remaining_time":0.3436243837},
{"learn":[3.197467568],"iteration":895,"passed_time":2.930646486,"remaining_time":0.3401643243},
{"learn":[3.195838544],"iteration":896,"passed_time":2.932193296,"remaining_time":0.3366955512},
{"learn":[3.195671746],"iteration":897,"passed_time":2.9339278,"remaining_time":0.3332523782},
{"learn":[3.194213094],"iteration":898,"passed_time":2.936949405,"remaining_time":0.3299576083},
{"learn":[3.192884691],"iteration":899,"passed_time":2.938729814,"remaining_time":0.3265255349},
{"learn":[3.188364239],"iteration":900,"passed_time":2.940421761,"remaining_time":0.3230874077},
{"learn":[3.185219478],"iteration":901,"passed_time":2.942043903,"remaining_time":0.3196455682},
{"learn":[3.184120387],"iteration":902,"passed_time":2.943635215,"remaining_time":0.3162044473},
{"learn":[3.183725321],"iteration":903,"passed_time":2.94526551,"remaining_time":0.3127715586},
{"learn":[3.181264554],"iteration":904,"passed_time":2.946928399,"remaining_time":0.3093460751},
{"learn":[3.180741589],"iteration":905,"passed_time":2.948570851,"remaining_time":0.305922362},
{"learn":[3.179782639],"iteration":906,"passed_time":2.950460528,"remaining_time":0.3025279262},
{"learn":[3.176377564],"iteration":907,"passed_time":2.952194452,"remaining_time":0.2991210238},
{"learn":[3.174078182],"iteration":908,"passed_time":2.953826798,"remaining_time":0.2957076333},
{"learn":[3.171242379],"iteration":909,"passed_time":2.955391147,"remaining_time":0.2922914321},
{"learn":[3.170421012],"iteration":910,"passed_time":2.95703894,"remaining_time":0.2888874486},
{"learn":[3.170087224],"iteration":911,"passed_time":2.958553165,"remaining_time":0.2854744282},
{"learn":[3.167303059],"iteration":912,"passed_time":2.960337537,"remaining_time":0.2820913097},
{"learn":[3.16705966],"iteration":913,"passed_time":2.963789735,"remaining_time":0.2788686184},
{"learn":[3.165667683],"iteration":914,"passed_time":2.965673663,"remaining_time":0.2754997392},
{"learn":[3.164689733],"iteration":915,"passed_time":2.967310245,"remaining_time":0.2721114199},
{"learn":[3.163311455],"iteration":916,"passed_time":2.96895201,"remaining_time":0.2687273902},
{"learn":[3.159425016],"iteration":917,"passed_time":2.970743406,"remaining_time":0.2653605221},
{"learn":[3.159327058],"iteration":918,"passed_time":2.97232685,"remaining_time":0.2619787539},
{"learn":[3.15819426],"iteration":919,"passed_time":2.974057877,"remaining_time":0.2586137284},
{"learn":[3.157086603],"iteration":920,"passed_time":2.975685136,"remaining_time":0.2552433504},
{"learn":[3.153354154],"iteration":921,"passed_time":2.979324024,"remaining_time":0.2520469348},
{"learn":[3.153261317],"iteration":922,"passed_time":2.98116451,"remaining_time":0.2486995312},
{"learn":[3.153168454],"iteration":923,"passed_time":2.982787987,"remaining_time":0.2453375401},
{"learn":[3.152080399],"iteration":924,"passed_time":2.984716202,"remaining_time":0.2420040164},
{"learn":[3.151635144],"iteration":925,"passed_time":2.986351546,"remaining_time":0.2386501236},
{"learn":[3.147762655],"iteration":926,"passed_time":2.987947403,"remaining_time":0.2352968289},
{"learn":[3.147172317],"iteration":927,"passed_time":2.989661654,"remaining_time":0.2319565076},
{"learn":[3.146254125],"iteration":928,"passed_time":2.993538697,"remaining_time":0.2287849812},
{"learn":[3.144869828],"iteration":929,"passed_time":2.995411099,"remaining_time":0.2254610505},
{"learn":[3.143466218],"iteration":930,"passed_time":2.997056875,"remaining_time":0.2221234419},
{"learn":[3.141919643],"iteration":931,"passed_time":2.998780856,"remaining_time":0.2187951698},
{"learn":[3.141054135],"iteration":932,"passed_time":3.000547147,"remaining_time":0.2154733749},
{"learn":[3.139390417],"iteration":933,"passed_time":3.002255205,"remaining_time":0.2121507961},
{"learn":[3.139025283],"iteration":934,"passed_time":3.003901723,"remaining_time":0.2088273925},
{"learn":[3.137824183],"iteration":935,"passed_time":3.008230793,"remaining_time":0.2056909944},
{"learn":[3.135620453],"iteration":936,"passed_time":3.01011444,"remaining_time":0.2023876304},
{"learn":[3.13443178],"iteration":937,"passed_time":3.011776211,"remaining_time":0.199072628},
{"learn":[3.132765713],"iteration":938,"passed_time":3.01339925,"remaining_time":0.1957586307},
{"learn":[3.131434124],"iteration":939,"passed_time":3.01503993,"remaining_time":0.1924493572},
{"learn":[3.128384262],"iteration":940,"passed_time":3.016691278,"remaining_time":0.189144299},
{"learn":[3.128120455],"iteration":941,"passed_time":3.018196511,"remaining_time":0.1858337555},
{"learn":[3.126314615],"iteration":942,"passed_time":3.01991179,"remaining_time":0.182539737},
{"learn":[3.125409666],"iteration":943,"passed_time":3.025569255,"remaining_time":0.1794829219},
{"learn":[3.123072589],"iteration":944,"passed_time":3.027363077,"remaining_time":0.1761957347},
{"learn":[3.122921099],"iteration":945,"passed_time":3.028920283,"remaining_time":0.172898198},
{"learn":[3.122182662],"iteration":946,"passed_time":3.030691092,"remaining_time":0.1696162913},
{"learn":[3.120040951],"iteration":947,"passed_time":3.032282369,"remaining_time":0.1663277249},
{"learn":[3.118767799],"iteration":948,"passed_time":3.033974721,"remaining_time":0.1630481673},
{"learn":[3.118203218],"iteration":949,"passed_time":3.038714617,"remaining_time":0.1599323483},
{"learn":[3.116343362],"iteration":950,"passed_time":3.041400815,"remaining_time":0.1567072975},
{"learn":[3.11480829],"iteration":951,"passed_time":3.043884655,"remaining_time":0.1534731759},
{"learn":[3.112607903],"iteration":952,"passed_time":3.046460918,"remaining_time":0.1502451869},
{"learn":[3.111661241],"iteration":953,"passed_time":3.052843522,"remaining_time":0.1472020985},
{"learn":[3.110249676],"iteration":954,"passed_time":3.05519132,"remaining_time":0.1439618946},
{"learn":[3.107333579],"iteration":955,"passed_time":3.057524228,"remaining_time":0.1407228724},
{"learn":[3.107149851],"iteration":956,"passed_time":3.059793513,"remaining_time":0.1374828851},
{"learn":[3.106867336],"iteration":957,"passed_time":3.067144956,"remaining_time":0.1344677329},
{"learn":[3.10364681],"iteration":958,"passed_time":3.071799191,"remaining_time":0.131328224},
{"learn":[3.102703811],"iteration":959,"passed_time":3.074223155,"remaining_time":0.1280926315},
{"learn":[3.101469264],"iteration":960,"passed_time":3.076444267,"remaining_time":0.1248504957},
{"learn":[3.09863569],"iteration":961,"passed_time":3.078854686,"remaining_time":0.1216179606},
{"learn":[3.09645939],"iteration":962,"passed_time":3.085934758,"remaining_time":0.1185665484},
{"learn":[3.096240186],"iteration":963,"passed_time":3.089320991,"remaining_time":0.1153688337},
{"learn":[3.094838828],"iteration":964,"passed_time":3.091725696,"remaining_time":0.1121351289},
{"learn":[3.094176802],"iteration":965,"passed_time":3.094366256,"remaining_time":0.1089114417},
{"learn":[3.093182279],"iteration":966,"passed_time":3.100933252,"remaining_time":0.1058229548},
{"learn":[3.090150687],"iteration":967,"passed_time":3.103716359,"remaining_time":0.1026021937},
{"learn":[3.088612829],"iteration":968,"passed_time":3.105663696,"remaining_time":0.09935559813},
{"learn":[3.087153684],"iteration":969,"passed_time":3.108108464,"remaining_time":0.09612706591},
{"learn":[3.085866843],"iteration":970,"passed_time":3.114368545,"remaining_time":0.09301409661},
{"learn":[3.082669094],"iteration":971,"passed_time":3.117036453,"remaining_time":0.08979117356},
{"learn":[3.081047548],"iteration":972,"passed_time":3.119510512,"remaining_time":0.08656401215},
{"learn":[3.079684322],"iteration":973,"passed_time":3.121973567,"remaining_time":0.08333810343},
{"learn":[3.07613431],"iteration":974,"passed_time":3.124336278,"remaining_time":0.08011118662},
{"learn":[3.074005935],"iteration":975,"passed_time":3.128978693,"remaining_time":0.07694209901},
{"learn":[3.072988853],"iteration":976,"passed_time":3.131123796,"remaining_time":0.07371120503},
{"learn":[3.072344268],"iteration":977,"passed_time":3.13345415,"remaining_time":0.07048669867},
{"learn":[3.070654438],"iteration":978,"passed_time":3.136295933,"remaining_time":0.06727498938},
{"learn":[3.069724506],"iteration":979,"passed_time":3.139371033,"remaining_time":0.06406879659},
{"learn":[3.067763166],"iteration":980,"passed_time":3.145355738,"remaining_time":0.06091922428},
{"learn":[3.066737893],"iteration":981,"passed_time":3.148147524,"remaining_time":0.05770535177},
{"learn":[3.065248174],"iteration":982,"passed_time":3.150894574,"remaining_time":0.05449156435},
{"learn":[3.063186837],"iteration":983,"passed_time":3.153602107,"remaining_time":0.05127808304},
{"learn":[3.062880371],"iteration":984,"passed_time":3.155306063,"remaining_time":0.04805034614},
{"learn":[3.061288645],"iteration":985,"passed_time":3.158315585,"remaining_time":0.04484423752},
{"learn":[3.059970575],"iteration":986,"passed_time":3.159952364,"remaining_time":0.04162044654},
{"learn":[3.059576341],"iteration":987,"passed_time":3.161555462,"remaining_time":0.03839945905},
{"learn":[3.058175919],"iteration":988,"passed_time":3.163354635,"remaining_time":0.03518392415},
{"learn":[3.056830702],"iteration":989,"passed_time":3.164929703,"remaining_time":0.03196898689},
{"learn":[3.056336579],"iteration":990,"passed_time":3.166597158,"remaining_time":0.0287581982},
{"learn":[3.055810414],"iteration":991,"passed_time":3.16817792,"remaining_time":0.02554982193},
{"learn":[3.055476518],"iteration":992,"passed_time":3.169785252,"remaining_time":0.02234491115},
{"learn":[3.053331734],"iteration":993,"passed_time":3.172883204,"remaining_time":0.0191522125},
{"learn":[3.050890374],"iteration":994,"passed_time":3.174782346,"remaining_time":0.01595368013},
{"learn":[3.04972623],"iteration":995,"passed_time":3.176852864,"remaining_time":0.01275844524},
{"learn":[3.047217327],"iteration":996,"passed_time":3.178557581,"remaining_time":0.00956436584},
{"learn":[3.047155483],"iteration":997,"passed_time":3.180057927,"remaining_time":0.006372861578},
{"learn":[3.04430671],"iteration":998,"passed_time":3.181657537,"remaining_time":0.003184842379},
{"learn":[3.042664195],"iteration":999,"passed_time":3.183752561,"remaining_time":0}
]}